Workbook
Name Print_Area_MI: 'MANHOLES (1)'!$V$53:$IU$1804
Name Print_Area_MI: 'SEWERS (1)'!$A$3:$AB$69
Name Print_Area_MI: 'WATERMAIN (1)'!$Y$84:$IU$1816
Name Print_Titles_MI: 'MANHOLES (1)'!$1804:$65536
Name Print_Titles_MI: 'WATERMAIN (1)'!$3:$1816

Sheet MANHOLES (1)
D1: TOPSITE CONTRACTING LIMITED | G1: MANHOLE & CATCHBASIN ESTIMATE | U1: =B2 -> 0
A2: PROJECT | U2: =G1 -> MANHOLE & CATCHBASIN ESTIMATE
A3: JOB #NO | E3: $/CM TRUCKING | F3: 10 | H3: FSTfctr | I3: 1
E4: $/CM CONCRETE | F4: 250 | H4: PSTfct | I4: 1 | K4: LABOR/HR | L4: 110 | O4: =IF(F7=1,"METRIC","IMPERIAL") -> METRIC | P4: =O4 -> METRIC | Q4: =O4 -> METRIC
A5: Date: | E5: %DISCOUNT | F5: 0.35 | H5: Mod$/m | I5: 718
E6: MARGIN FACTOR | F6: 1.1 | H6: MH F&C $ | I6: 375 | K6: DSC/TX FCTR | L6: =(100-F5)/100*I3*I4 -> 0.9965
C7: =O4 -> METRIC | E7: METRIC 1/ IMPER 0 | F7: 1 | H7: CB F&C $ | I7: 500 | K7: FR+CVR m | L7: 0.3
A9: Item | B9: MH Description | C9: Top El. | D9: Low Inv | E9: Hi Inv | F9: Pipe Out | G9: ST1/L2 | H9: Add$Mtrls | I9: Add$L&E | J9: Depth m | K9: Drop m | L9: MHdia-mm | M9: PCovrall | N9: $Precast | O9: $Conc | P9: $Fr&Cov | Q9: $Matrl | R9: $L&E | S9: $Trkng | T9: $/VM | U9: TOTAL $ | V9: SALE$
A11: 1 | J11: =(C11-D11)*IF(F$7=1,1,0.3049) -> 0 | K11: =IF(E11=0,0,(D11-E11)*IF(F$7=1,1,0.3049)) -> 0 | L11: =IF(F11=0,0,IF((G11=1),HLOOKUP(F11,B$65:F$66,2),HLOOKUP(F11,H$65:L$66,2))) -> 0 | M11: =IF(J11=0,0,J11-L$7+0.3*F11/1000+0.3) -> 0 | N11: =(IF(L11=0,0,IF(L11<1501,VLOOKUP(L11+M11,C$69:D$117,2),VLOOKUP(L11+M11,E$69:F$113,2))+(L$7-0.15)*I$5)*I$3*I$4*(1-F$5)) -> 0 | O11: =(((L11/1000)^2*PI()/4*F11/1000)-PI()/4*(F11/1000)^2*L11/1000+L11/1000)*F$4 -> 0 | P11: =IF(L11=0,0,I$6*I$3*I$4) -> 0 | Q11: =H11+N11+O11+P11 -> 0 | R11: =(L11=1200)*(15*L$4+L$4*M11)+(L11=1500)*(20*L$4+1.3*L$4*M11)+(L11=1800)*(30*L$4+1.5*L$4*M11)+(L11=2400)*(40*L$4+2*L$4*M11)+(L11=3000)*(50*L$4+2.5*L$4*M11)+(L11=3600)*(60*L$4+3*L$4*M11)+I11 -> 0 | S11: =F$3*(J11*(0.001*L11*1.3)^2*PI()/4) -> 0 | T11: =IF(L11=0,0,(Q11+R11+S11)/J11) -> 0 | U11: =Q11+R11+S11 -> 0 | V11: =U11*F$6 -> 0
A12: =1+A11 -> 2 | J12: =(C12-D12)*IF(F$7=1,1,0.3049) -> 0 | K12: =IF(E12=0,0,(D12-E12)*IF(F$7=1,1,0.3049)) -> 0 | L12: =IF(F12=0,0,IF((G12=1),HLOOKUP(F12,B$65:F$66,2),HLOOKUP(F12,H$65:L$66,2))) -> 0 | M12: =IF(J12=0,0,J12-L$7+0.3*F12/1000+0.3) -> 0 | N12: =(IF(L12=0,0,IF(L12<1501,VLOOKUP(L12+M12,C$69:D$117,2),VLOOKUP(L12+M12,E$69:F$113,2))+(L$7-0.15)*I$5)*I$3*I$4*(1-F$5)) -> 0 | O12: =(((L12/1000)^2*PI()/4*F12/1000)-PI()/4*(F12/1000)^2*L12/1000+L12/1000)*F$4 -> 0 | P12: =IF(L12=0,0,I$6*I$3*I$4) -> 0 | Q12: =H12+N12+O12+P12 -> 0 | R12: =(L12=1200)*(15*L$4+L$4*M12)+(L12=1500)*(20*L$4+1.3*L$4*M12)+(L12=1800)*(30*L$4+1.5*L$4*M12)+(L12=2400)*(40*L$4+2*L$4*M12)+(L12=3000)*(50*L$4+2.5*L$4*M12)+(L12=3600)*(60*L$4+3*L$4*M12)+I12 -> 0 | S12: =F$3*(J12*(0.001*L12*1.3)^2*PI()/4) -> 0 | T12: =IF(L12=0,0,(Q12+R12+S12)/J12) -> 0 | U12: =Q12+R12+S12 -> 0 | V12: =U12*F$6 -> 0
A13: =1+A12 -> 3 | J13: =(C13-D13)*IF(F$7=1,1,0.3049) -> 0 | K13: =IF(E13=0,0,(D13-E13)*IF(F$7=1,1,0.3049)) -> 0 | L13: =IF(F13=0,0,IF((G13=1),HLOOKUP(F13,B$65:F$66,2),HLOOKUP(F13,H$65:L$66,2))) -> 0 | M13: =IF(J13=0,0,J13-L$7+0.3*F13/1000+0.3) -> 0 | N13: =(IF(L13=0,0,IF(L13<1501,VLOOKUP(L13+M13,C$69:D$117,2),VLOOKUP(L13+M13,E$69:F$113,2))+(L$7-0.15)*I$5)*I$3*I$4*(1-F$5)) -> 0 | O13: =(((L13/1000)^2*PI()/4*F13/1000)-PI()/4*(F13/1000)^2*L13/1000+L13/1000)*F$4 -> 0 | P13: =IF(L13=0,0,I$6*I$3*I$4) -> 0 | Q13: =H13+N13+O13+P13 -> 0 | R13: =(L13=1200)*(15*L$4+L$4*M13)+(L13=1500)*(20*L$4+1.3*L$4*M13)+(L13=1800)*(30*L$4+1.5*L$4*M13)+(L13=2400)*(40*L$4+2*L$4*M13)+(L13=3000)*(50*L$4+2.5*L$4*M13)+(L13=3600)*(60*L$4+3*L$4*M13)+I13 -> 0 | S13: =F$3*(J13*(0.001*L13*1.3)^2*PI()/4) -> 0 | T13: =IF(L13=0,0,(Q13+R13+S13)/J13) -> 0 | U13: =Q13+R13+S13 -> 0 | V13: =U13*F$6 -> 0
A14: =1+A13 -> 4 | J14: =(C14-D14)*IF(F$7=1,1,0.3049) -> 0 | K14: =IF(E14=0,0,(D14-E14)*IF(F$7=1,1,0.3049)) -> 0 | L14: =IF(F14=0,0,IF((G14=1),HLOOKUP(F14,B$65:F$66,2),HLOOKUP(F14,H$65:L$66,2))) -> 0 | M14: =IF(J14=0,0,J14-L$7+0.3*F14/1000+0.3) -> 0 | N14: =(IF(L14=0,0,IF(L14<1501,VLOOKUP(L14+M14,C$69:D$117,2),VLOOKUP(L14+M14,E$69:F$113,2))+(L$7-0.15)*I$5)*I$3*I$4*(1-F$5)) -> 0 | O14: =(((L14/1000)^2*PI()/4*F14/1000)-PI()/4*(F14/1000)^2*L14/1000+L14/1000)*F$4 -> 0 | P14: =IF(L14=0,0,I$6*I$3*I$4) -> 0 | Q14: =H14+N14+O14+P14 -> 0 | R14: =(L14=1200)*(15*L$4+L$4*M14)+(L14=1500)*(20*L$4+1.3*L$4*M14)+(L14=1800)*(30*L$4+1.5*L$4*M14)+(L14=2400)*(40*L$4+2*L$4*M14)+(L14=3000)*(50*L$4+2.5*L$4*M14)+(L14=3600)*(60*L$4+3*L$4*M14)+I14 -> 0 | S14: =F$3*(J14*(0.001*L14*1.3)^2*PI()/4) -> 0 | T14: =IF(L14=0,0,(Q14+R14+S14)/J14) -> 0 | U14: =Q14+R14+S14 -> 0 | V14: =U14*F$6 -> 0
A15: =1+A14 -> 5 | J15: =(C15-D15)*IF(F$7=1,1,0.3049) -> 0 | K15: =IF(E15=0,0,(D15-E15)*IF(F$7=1,1,0.3049)) -> 0 | L15: =IF(F15=0,0,IF((G15=1),HLOOKUP(F15,B$65:F$66,2),HLOOKUP(F15,H$65:L$66,2))) -> 0 | M15: =IF(J15=0,0,J15-L$7+0.3*F15/1000+0.3) -> 0 | N15: =(IF(L15=0,0,IF(L15<1501,VLOOKUP(L15+M15,C$69:D$117,2),VLOOKUP(L15+M15,E$69:F$113,2))+(L$7-0.15)*I$5)*I$3*I$4*(1-F$5)) -> 0 | O15: =(((L15/1000)^2*PI()/4*F15/1000)-PI()/4*(F15/1000)^2*L15/1000+L15/1000)*F$4 -> 0 | P15: =IF(L15=0,0,I$6*I$3*I$4) -> 0 | Q15: =H15+N15+O15+P15 -> 0 | R15: =(L15=1200)*(15*L$4+L$4*M15)+(L15=1500)*(20*L$4+1.3*L$4*M15)+(L15=1800)*(30*L$4+1.5*L$4*M15)+(L15=2400)*(40*L$4+2*L$4*M15)+(L15=3000)*(50*L$4+2.5*L$4*M15)+(L15=3600)*(60*L$4+3*L$4*M15)+I15 -> 0 | S15: =F$3*(J15*(0.001*L15*1.3)^2*PI()/4) -> 0 | T15: =IF(L15=0,0,(Q15+R15+S15)/J15) -> 0 | U15: =Q15+R15+S15 -> 0 | V15: =U15*F$6 -> 0
A16: =1+A15 -> 6 | J16: =(C16-D16)*IF(F$7=1,1,0.3049) -> 0 | K16: =IF(E16=0,0,(D16-E16)*IF(F$7=1,1,0.3049)) -> 0 | L16: =IF(F16=0,0,IF((G16=1),HLOOKUP(F16,B$65:F$66,2),HLOOKUP(F16,H$65:L$66,2))) -> 0 | M16: =IF(J16=0,0,J16-L$7+0.3*F16/1000+0.3) -> 0 | N16: =(IF(L16=0,0,IF(L16<1501,VLOOKUP(L16+M16,C$69:D$117,2),VLOOKUP(L16+M16,E$69:F$113,2))+(L$7-0.15)*I$5)*I$3*I$4*(1-F$5)) -> 0 | O16: =(((L16/1000)^2*PI()/4*F16/1000)-PI()/4*(F16/1000)^2*L16/1000+L16/1000)*F$4 -> 0 | P16: =IF(L16=0,0,I$6*I$3*I$4) -> 0 | Q16: =H16+N16+O16+P16 -> 0 | R16: =(L16=1200)*(15*L$4+L$4*M16)+(L16=1500)*(20*L$4+1.3*L$4*M16)+(L16=1800)*(30*L$4+1.5*L$4*M16)+(L16=2400)*(40*L$4+2*L$4*M16)+(L16=3000)*(50*L$4+2.5*L$4*M16)+(L16=3600)*(60*L$4+3*L$4*M16)+I16 -> 0 | S16: =F$3*(J16*(0.001*L16*1.3)^2*PI()/4) -> 0 | T16: =IF(L16=0,0,(Q16+R16+S16)/J16) -> 0 | U16: =Q16+R16+S16 -> 0 | V16: =U16*F$6 -> 0
A17: =1+A16 -> 7 | J17: =(C17-D17)*IF(F$7=1,1,0.3049) -> 0 | K17: =IF(E17=0,0,(D17-E17)*IF(F$7=1,1,0.3049)) -> 0 | L17: =IF(F17=0,0,IF((G17=1),HLOOKUP(F17,B$65:F$66,2),HLOOKUP(F17,H$65:L$66,2))) -> 0 | M17: =IF(J17=0,0,J17-L$7+0.3*F17/1000+0.3) -> 0 | N17: =(IF(L17=0,0,IF(L17<1501,VLOOKUP(L17+M17,C$69:D$117,2),VLOOKUP(L17+M17,E$69:F$113,2))+(L$7-0.15)*I$5)*I$3*I$4*(1-F$5)) -> 0 | O17: =(((L17/1000)^2*PI()/4*F17/1000)-PI()/4*(F17/1000)^2*L17/1000+L17/1000)*F$4 -> 0 | P17: =IF(L17=0,0,I$6*I$3*I$4) -> 0 | Q17: =H17+N17+O17+P17 -> 0 | R17: =(L17=1200)*(15*L$4+L$4*M17)+(L17=1500)*(20*L$4+1.3*L$4*M17)+(L17=1800)*(30*L$4+1.5*L$4*M17)+(L17=2400)*(40*L$4+2*L$4*M17)+(L17=3000)*(50*L$4+2.5*L$4*M17)+(L17=3600)*(60*L$4+3*L$4*M17)+I17 -> 0 | S17: =F$3*(J17*(0.001*L17*1.3)^2*PI()/4) -> 0 | T17: =IF(L17=0,0,(Q17+R17+S17)/J17) -> 0 | U17: =Q17+R17+S17 -> 0 | V17: =U17*F$6 -> 0
A18: =1+A17 -> 8 | J18: =(C18-D18)*IF(F$7=1,1,0.3049) -> 0 | K18: =IF(E18=0,0,(D18-E18)*IF(F$7=1,1,0.3049)) -> 0 | L18: =IF(F18=0,0,IF((G18=1),HLOOKUP(F18,B$65:F$66,2),HLOOKUP(F18,H$65:L$66,2))) -> 0 | M18: =IF(J18=0,0,J18-L$7+0.3*F18/1000+0.3) -> 0 | N18: =(IF(L18=0,0,IF(L18<1501,VLOOKUP(L18+M18,C$69:D$117,2),VLOOKUP(L18+M18,E$69:F$113,2))+(L$7-0.15)*I$5)*I$3*I$4*(1-F$5)) -> 0 | O18: =(((L18/1000)^2*PI()/4*F18/1000)-PI()/4*(F18/1000)^2*L18/1000+L18/1000)*F$4 -> 0 | P18: =IF(L18=0,0,I$6*I$3*I$4) -> 0 | Q18: =H18+N18+O18+P18 -> 0 | R18: =(L18=1200)*(15*L$4+L$4*M18)+(L18=1500)*(20*L$4+1.3*L$4*M18)+(L18=1800)*(30*L$4+1.5*L$4*M18)+(L18=2400)*(40*L$4+2*L$4*M18)+(L18=3000)*(50*L$4+2.5*L$4*M18)+(L18=3600)*(60*L$4+3*L$4*M18)+I18 -> 0 | S18: =F$3*(J18*(0.001*L18*1.3)^2*PI()/4) -> 0 | T18: =IF(L18=0,0,(Q18+R18+S18)/J18) -> 0 | U18: =Q18+R18+S18 -> 0 | V18: =U18*F$6 -> 0
A19: =1+A18 -> 9 | J19: =(C19-D19)*IF(F$7=1,1,0.3049) -> 0 | K19: =IF(E19=0,0,(D19-E19)*IF(F$7=1,1,0.3049)) -> 0 | L19: =IF(F19=0,0,IF((G19=1),HLOOKUP(F19,B$65:F$66,2),HLOOKUP(F19,H$65:L$66,2))) -> 0 | M19: =IF(J19=0,0,J19-L$7+0.3*F19/1000+0.3) -> 0 | N19: =(IF(L19=0,0,IF(L19<1501,VLOOKUP(L19+M19,C$69:D$117,2),VLOOKUP(L19+M19,E$69:F$113,2))+(L$7-0.15)*I$5)*I$3*I$4*(1-F$5)) -> 0 | O19: =(((L19/1000)^2*PI()/4*F19/1000)-PI()/4*(F19/1000)^2*L19/1000+L19/1000)*F$4 -> 0 | P19: =IF(L19=0,0,I$6*I$3*I$4) -> 0 | Q19: =H19+N19+O19+P19 -> 0 | R19: =(L19=1200)*(15*L$4+L$4*M19)+(L19=1500)*(20*L$4+1.3*L$4*M19)+(L19=1800)*(30*L$4+1.5*L$4*M19)+(L19=2400)*(40*L$4+2*L$4*M19)+(L19=3000)*(50*L$4+2.5*L$4*M19)+(L19=3600)*(60*L$4+3*L$4*M19)+I19 -> 0 | S19: =F$3*(J19*(0.001*L19*1.3)^2*PI()/4) -> 0 | T19: =IF(L19=0,0,(Q19+R19+S19)/J19) -> 0 | U19: =Q19+R19+S19 -> 0 | V19: =U19*F$6 -> 0
A20: =1+A19 -> 10 | J20: =(C20-D20)*IF(F$7=1,1,0.3049) -> 0 | K20: =IF(E20=0,0,(D20-E20)*IF(F$7=1,1,0.3049)) -> 0 | L20: =IF(F20=0,0,IF((G20=1),HLOOKUP(F20,B$65:F$66,2),HLOOKUP(F20,H$65:L$66,2))) -> 0 | M20: =IF(J20=0,0,J20-L$7+0.3*F20/1000+0.3) -> 0 | N20: =(IF(L20=0,0,IF(L20<1501,VLOOKUP(L20+M20,C$69:D$117,2),VLOOKUP(L20+M20,E$69:F$113,2))+(L$7-0.15)*I$5)*I$3*I$4*(1-F$5)) -> 0 | O20: =(((L20/1000)^2*PI()/4*F20/1000)-PI()/4*(F20/1000)^2*L20/1000+L20/1000)*F$4 -> 0 | P20: =IF(L20=0,0,I$6*I$3*I$4) -> 0 | Q20: =H20+N20+O20+P20 -> 0 | R20: =(L20=1200)*(15*L$4+L$4*M20)+(L20=1500)*(20*L$4+1.3*L$4*M20)+(L20=1800)*(30*L$4+1.5*L$4*M20)+(L20=2400)*(40*L$4+2*L$4*M20)+(L20=3000)*(50*L$4+2.5*L$4*M20)+(L20=3600)*(60*L$4+3*L$4*M20)+I20 -> 0 | S20: =F$3*(J20*(0.001*L20*1.3)^2*PI()/4) -> 0 | T20: =IF(L20=0,0,(Q20+R20+S20)/J20) -> 0 | U20: =Q20+R20+S20 -> 0 | V20: =U20*F$6 -> 0
A21: =1+A20 -> 11 | J21: =(C21-D21)*IF(F$7=1,1,0.3049) -> 0 | K21: =IF(E21=0,0,(D21-E21)*IF(F$7=1,1,0.3049)) -> 0 | L21: =IF(F21=0,0,IF((G21=1),HLOOKUP(F21,B$65:F$66,2),HLOOKUP(F21,H$65:L$66,2))) -> 0 | M21: =IF(J21=0,0,J21-L$7+0.3*F21/1000+0.3) -> 0 | N21: =(IF(L21=0,0,IF(L21<1501,VLOOKUP(L21+M21,C$69:D$117,2),VLOOKUP(L21+M21,E$69:F$113,2))+(L$7-0.15)*I$5)*I$3*I$4*(1-F$5)) -> 0 | O21: =(((L21/1000)^2*PI()/4*F21/1000)-PI()/4*(F21/1000)^2*L21/1000+L21/1000)*F$4 -> 0 | P21: =IF(L21=0,0,I$6*I$3*I$4) -> 0 | Q21: =H21+N21+O21+P21 -> 0 | R21: =(L21=1200)*(15*L$4+L$4*M21)+(L21=1500)*(20*L$4+1.3*L$4*M21)+(L21=1800)*(30*L$4+1.5*L$4*M21)+(L21=2400)*(40*L$4+2*L$4*M21)+(L21=3000)*(50*L$4+2.5*L$4*M21)+(L21=3600)*(60*L$4+3*L$4*M21)+I21 -> 0 | S21: =F$3*(J21*(0.001*L21*1.3)^2*PI()/4) -> 0 | T21: =IF(L21=0,0,(Q21+R21+S21)/J21) -> 0 | U21: =Q21+R21+S21 -> 0 | V21: =U21*F$6 -> 0
A22: =1+A21 -> 12 | J22: =(C22-D22)*IF(F$7=1,1,0.3049) -> 0 | K22: =IF(E22=0,0,(D22-E22)*IF(F$7=1,1,0.3049)) -> 0 | L22: =IF(F22=0,0,IF((G22=1),HLOOKUP(F22,B$65:F$66,2),HLOOKUP(F22,H$65:L$66,2))) -> 0 | M22: =IF(J22=0,0,J22-L$7+0.3*F22/1000+0.3) -> 0 | N22: =(IF(L22=0,0,IF(L22<1501,VLOOKUP(L22+M22,C$69:D$117,2),VLOOKUP(L22+M22,E$69:F$113,2))+(L$7-0.15)*I$5)*I$3*I$4*(1-F$5)) -> 0 | O22: =(((L22/1000)^2*PI()/4*F22/1000)-PI()/4*(F22/1000)^2*L22/1000+L22/1000)*F$4 -> 0 | P22: =IF(L22=0,0,I$6*I$3*I$4) -> 0 | Q22: =H22+N22+O22+P22 -> 0 | R22: =(L22=1200)*(15*L$4+L$4*M22)+(L22=1500)*(20*L$4+1.3*L$4*M22)+(L22=1800)*(30*L$4+1.5*L$4*M22)+(L22=2400)*(40*L$4+2*L$4*M22)+(L22=3000)*(50*L$4+2.5*L$4*M22)+(L22=3600)*(60*L$4+3*L$4*M22)+I22 -> 0 | S22: =F$3*(J22*(0.001*L22*1.3)^2*PI()/4) -> 0 | T22: =IF(L22=0,0,(Q22+R22+S22)/J22) -> 0 | U22: =Q22+R22+S22 -> 0 | V22: =U22*F$6 -> 0
A23: =1+A22 -> 13 | J23: =(C23-D23)*IF(F$7=1,1,0.3049) -> 0 | K23: =IF(E23=0,0,(D23-E23)*IF(F$7=1,1,0.3049)) -> 0 | L23: =IF(F23=0,0,IF((G23=1),HLOOKUP(F23,B$65:F$66,2),HLOOKUP(F23,H$65:L$66,2))) -> 0 | M23: =IF(J23=0,0,J23-L$7+0.3*F23/1000+0.3) -> 0 | N23: =(IF(L23=0,0,IF(L23<1501,VLOOKUP(L23+M23,C$69:D$117,2),VLOOKUP(L23+M23,E$69:F$113,2))+(L$7-0.15)*I$5)*I$3*I$4*(1-F$5)) -> 0 | O23: =(((L23/1000)^2*PI()/4*F23/1000)-PI()/4*(F23/1000)^2*L23/1000+L23/1000)*F$4 -> 0 | P23: =IF(L23=0,0,I$6*I$3*I$4) -> 0 | Q23: =H23+N23+O23+P23 -> 0 | R23: =(L23=1200)*(15*L$4+L$4*M23)+(L23=1500)*(20*L$4+1.3*L$4*M23)+(L23=1800)*(30*L$4+1.5*L$4*M23)+(L23=2400)*(40*L$4+2*L$4*M23)+(L23=3000)*(50*L$4+2.5*L$4*M23)+(L23=3600)*(60*L$4+3*L$4*M23)+I23 -> 0 | S23: =F$3*(J23*(0.001*L23*1.3)^2*PI()/4) -> 0 | T23: =IF(L23=0,0,(Q23+R23+S23)/J23) -> 0 | U23: =Q23+R23+S23 -> 0 | V23: =U23*F$6 -> 0
... A46: =1+A45 -> 36 | J46: =(C46-D46)*IF(F$7=1,1,0.3049) -> 0 | K46: =IF(E46=0,0,(D46-E46)*IF(F$7=1,1,0.3049)) -> 0 | L46: =IF(F46=0,0,IF((G46=1),HLOOKUP(F46,B$65:F$66,2),HLOOKUP(F46,H$65:L$66,2))) -> 0 | M46: =IF(J46=0,0,J46-L$7+0.3*F46/1000+0.3) -> 0 | N46: =(IF(L46=0,0,IF(L46<1501,VLOOKUP(L46+M46,C$69:D$117,2),VLOOKUP(L46+M46,E$69:F$113,2))+(L$7-0.15)*I$5)*I$3*I$4*(1-F$5)) -> 0 | O46: =(((L46/1000)^2*PI()/4*F46/1000)-PI()/4*(F46/1000)^2*L46/1000+L46/1000)*F$4 -> 0 | P46: =IF(L46=0,0,I$6*I$3*I$4) -> 0 | Q46: =H46+N46+O46+P46 -> 0 | R46: =(L46=1200)*(15*L$4+L$4*M46)+(L46=1500)*(20*L$4+1.3*L$4*M46)+(L46=1800)*(30*L$4+1.5*L$4*M46)+(L46=2400)*(40*L$4+2*L$4*M46)+(L46=3000)*(50*L$4+2.5*L$4*M46)+(L46=3600)*(60*L$4+3*L$4*M46)+I46 -> 0 | S46: =F$3*(J46*(0.001*L46*1.3)^2*PI()/4) -> 0 | T46: =IF(L46=0,0,(Q46+R46+S46)/J46) -> 0 | U46: =Q46+R46+S46 -> 0 | V46: =U46*F$6 -> 0
A48: MANHOLE TOTALS | H48: =SUM(H9:H46) -> 0 | I48: =SUM(I9:I46) -> 0 | N48: =SUM(N11:N46) -> 0 | O48: =SUM(O11:O46) -> 0 | P48: =SUM(P11:P46) -> 0 | Q48: =SUM(Q11:Q46) -> 0 | R48: =SUM(R11:R46) -> 0 | S48: =SUM(S11:S46) -> 0 | U48: =SUM(U11:U46) -> 0 | V48: =SUM(V11:V46) -> 0
B51: CATCHBASINS
B52: ITEMS | C52: QNTY | D52: WALL" | E52: DPTHm | F52: $GT ea | G52: $/ADDMAT | H52: $/AD L&E | I52: $PRECST | J52: $CONC | K52: $FR&CV | L52: $MATRL | M52: $LAB&EQ | N52: $TRKNG | O52: $ EACH | P52: TOTAL $ | Q52: $ SALE/ | S52: TOTALS | T52: $COST | U52: $MARGIN | V52: $SALE
A53: 1 | B53: SINGLE C.B.'S | D53: 4 | E53: 2.2 | F53: 0 | G53: 0 | H53: 0 | I53: =(IF(D53=4,F$115,F$116)*L6*(E53-L7)+F53*I3*I$4+(L$7-0.15)*I$5)*C53 -> 0 | J53: =C53*0.5*F$4 -> 0 | K53: =C53*I$7*I$3*I$4 -> 0 | L53: =G53*C53+I53+J53+K53 -> 0 | M53: =C53*(C$59+H53) -> 0 | N53: =C53*E53*1*F$3 -> 0 | O53: =IF(C53=0,0,(L53+M53+N53)/C53) -> 0 | P53: =L53+M53+N53 -> 0 | Q53: =O53*F$6 -> 0
A54: 2 | B54: DOUBLE C.B.'S | D54: 4 | E54: 2.2 | F54: 0 | G54: 0 | H54: 0 | I54: =(F119*L6*(E54-L7)+F54*I3*I4+(L7-0.15)*I5*2)*C54 -> 0 | J54: =C54*1*F$4 -> 0 | K54: =C54*I$7*2*I$3*I$4 -> 0 | L54: =G54*C54+I54+J54+K54 -> 0 | M54: =C54*(C$60+H54) -> 0 | N54: =C54*E54*1.8*F$3 -> 0 | O54: =IF(C54=0,0,(L54+M54+N54)/C54) -> 0 | P54: =L54+M54+N54 -> 0 | Q54: =O54*F$6 -> 0 | S54: MAERIALS | T54: =Q48+L57 -> 0 | U54: =(F6-1)*T54 -> 0 | V54: =T54+U54 -> 0
A55: 3 | B55: DITCH INLT CB'S | D55: 4 | E55: 2.2 | F55: 0 | G55: 0 | H55: 0 | I55: =(F117*L$6*(E55-L$7)+F55*I$3*I$4+(L7-0.15)*I$5)*C55 -> 0 | J55: =C55*0.5*F$4 -> 0 | K55: =C55*(F59*L6) -> 0 | L55: =G55*C55+I55+J55+K55 -> 0 | M55: =C55*(C$61+H55) -> 0 | N55: =C55*E55*1*F$3 -> 0 | O55: =IF(C55=0,0,(L55+M55+N55)/C55) -> 0 | P55: =L55+M55+N55 -> 0 | Q55: =O55*F$6 -> 0 | S55: LAB & EQ. | T55: =R48+M57 -> 0 | U55: =(F6-1)*T55 -> 0 | V55: =T55+U55 -> 0
A56: 4 | B56: DDITCH INLT CB'S | D56: 4 | E56: 2.2 | F56: 0 | G56: 0 | H56: 0 | I56: =(F118*L$6*(E56-L$7)+F56*I$3*I$4+(L7-0.15)*I$5)*C56 -> 0 | J56: =C56*1*F$4 -> 0 | K56: =C56*(F60*L6) -> 0 | L56: =G56*C56+I56+J56+K56 -> 0 | M56: =C56*(C$62+H56) -> 0 | N56: =C56*E56*1.8*F$3 -> 0 | O56: =IF(C56=0,0,(L56+M56+N56)/C56) -> 0 | P56: =L56+M56+N56 -> 0 | Q56: =O56*F$6 -> 0 | S56: TRUCKING | T56: =S48+N57 -> 0 | U56: =(F6-1)*T56 -> 0 | V56: =T56+U56 -> 0
A57: CATCHBASIN TOTALS | C57: =SUM(C53:C56) -> 0 | G57: =SUM(G53:G56) -> 0 | H57: =SUM(H53:H56) -> 0 | I57: =SUM(I53:I56) -> 0 | J57: =SUM(J53:J56) -> 0 | K57: =SUM(K53:K56) -> 0 | L57: =SUM(L53:L56) -> 0 | M57: =SUM(M53:M56) -> 0 | N57: =SUM(N53:N56) -> 0 | P57: =SUM(P53:P56) -> 0 | Q57: =SUM(Q53:Q56) -> 0 | S57: BID PRICE | T57: =SUM(T54:T56) -> 0 | U57: =(F6-1)*T57 -> 0 | V57: =T57+U57 -> 0
B59: LABOR SCB | C59: 200 | E59: DICB F&C $ | F59: 465
B60: LABOR DCB | C60: 250 | E60: DDICB F&C $ | F60: 715
B61: LABOR DICB | C61: 220
B62: LABOR DDICB | C62: 280
A64: LOOKUP TABLE FOR MANHOLE SIZE
A65: PipeIDstr | B65: 50 | C65: 601 | D65: 826 | E65: 1051 | F65: 1501 | G65: PipeIDang | H65: 50 | I65: 451 | J65: 601 | K65: 826 | L65: 1051
A66: MH dia | B66: 1200 | C66: 1500 | D66: 1800 | E66: 2400 | F66: =NA() -> #N/A | G66: MHdia mm | H66: 1200 | I66: 1500 | J66: 1800 | K66: 2400 | L66: =NA() -> #N/A
A69: LOOKUP TABLE | C69: MH Prices Feb 2020 | G69: NOTE: Paste copy in boxed area of MH Pricer
C70: 1200 | D70: 1500 | E70: 1800 | F70: 2400 | G70: to this boxed area. USING "PASTE SPECIAL"
C71: 1201 | D71: 1707.103 | E71: 1801.67 | F71: 5132.8757 | G71: AND OPTING FOR TEXT ONLY.
C72: 1201.33 | D72: 1971.0004 | E72: 1802 | F72: 5701.6366
C73: 1201.67 | D73: 2235.8977 | E73: 1802.33 | F73: 6270.3976
C74: 1202 | D74: 2499.7951 | E74: 1802.67 | F74: 6840.2575
C75: 1202.33 | D75: 2426.5169 | E75: 1803 | F75: 7409.0185
C76: 1202.67 | D76: 2691.4143 | E76: 1803.33 | F76: 7977.7795
C77: 1203 | D77: 2955.3117 | E77: 1803.67 | F77: 8547.6393
C78: 1203.33 | D78: 3219.209 | E78: 1804 | F78: 8085.0632
C79: 1203.67 | D79: 3483.1064 | E79: 1804.33 | F79: 8348.9606
C80: 1204 | D80: 3748.0037 | E80: 1804.67 | F80: 8612.858
C81: 1204.33 | D81: 4011.9011 | E81: 1805 | F81: 8876.7553
C82: 1204.67 | D82: 4275.7985 | E82: 1805.33 | F82: 9141.6527
C83: 1205 | D83: 4539.6958 | E83: 1805.67 | F83: 9405.5501
... C92: 1208 | D92: 8401.2721 | E92: 1808.67 | F92: 13266.126
C93: 1208.33 | D93: 8665.1694 | E93: 2400 | F93: #N/A
C94: 1208.67 | D94: 8929.0668 | E94: 2402 | F94: 10823.35
C95: 1500 | D95: #N/A | E95: 2402.33 | F95: 11837.339
C96: 1501.33 | D96: 3336.796 | E96: 2402.67 | F96: 12852.329
C97: 1501.67 | D97: 3736.792 | E97: 2403 | F97: 13866.319
C98: 1502 | D98: 4137.788 | E98: 2403.33 | F98: 14880.309
C99: 1502.33 | D99: 4537.784 | E99: 2403.67 | F99: 15895.299
C100: 1502.67 | D100: 4937.78 | E100: 2404 | F100: 14894.097
C101: 1503 | D101: 5337.776 | E101: 2404.33 | F101: 15157.995
C102: 1503.33 | D102: 5738.772 | E102: 2404.67 | F102: 15421.892
C103: 1503.67 | D103: 6138.768 | E103: 2405 | F103: 15685.789
C104: 1504 | D104: 6023.3542 | E104: 2405.33 | F104: 15949.687
C105: 1504.33 | D105: 6287.2516 | E105: 2405.67 | F105: 16214.584
C106: 1504.67 | D106: 6551.149 | E106: 2406 | F106: 17961.981
C107: 1505 | D107: 6816.0463 | E107: 2406.33 | F107: 18225.879
... C114: 1507.33 | D114: 10148.828 | E114: 2408.67 | F114: 20075.16
C115: 1507.67 | D115: 10412.725 | E115: Std.CB 4.5" | F115: 518.5
C116: 1508 | D116: 10676.623 | E116: Std.CB 6.0" | F116: 700.9
C117: 1508.33 | D117: 10940.52 | E117: Dinlet 24x24 | F117: 700.9
C118: 1508.67 | D118: 11205.417 | E118: Dinlet 24x48 | F118: 1137.8
E119: DCB | F119: 1006.2

Sheet SEWERS (1)
C1: TOPSITE CONTRACTING LIMITED | G1: SEWER RUNS ESTIMATE | AB1: =B2 -> 0
A2: ='MANHOLES (1)'!A2 -> PROJECT | B2: ='MANHOLES (1)'!B2 -> 0 | AB2: =G1 -> SEWER RUNS ESTIMATE
C3: Min Trench Width m | F3: 1.2 | G3: $/ImpT Stone | I3: 22 | L3: 100PVC$/m | M3: =C87 -> 12 | O3: %Efficiency | P3: 100 | U3: ProvTax | V3: 1
C4: Pipe Cover m | F4: 0.3 | G4: $/Mt Stone | I4: 35 | L4: 150PVC$/m | M4: =D87 -> 24 | O4: M/Imp (1/0) | P4: 1 | U4: FedTax | V4: 1
A5: ='MANHOLES (1)'!A5 -> Date: | B5: ='MANHOLES (1)'!B5 -> 0 | C5: M-Fin Grade | F5: 0 | G5: $/ImpTn Gran | I5: 10 | L5: 200PVC$/m | M5: =E87 -> 34 | O5: Margin Fctr | P5: 1.1 | Q5: ³³ | U5: CP Fctr | V5: =(1-P8/100)*V4*V3 -> 0.75
C6: Daycost $/Day | F6: 9000 | G6: $/Mt Gran | I6: 30 | L6: 250PVC$/m | M6: =F87 -> 51 | O6: OpenCutFctr | P6: 0.9 | U6: PC Fctr | V6: =(1-S4/100)*V3 -> 1
C7: $Xtra/Day | F7: 300 | G7: $Trucking/cm | I7: ='MANHOLES (1)'!F3 -> 10 | L7: 300PVC$/m | M7: =G87 -> 73 | O7: DualTrSep m | P7: 0.8
C8: Prdtn M/Day | F8: 65 | L8: 375PVC$/m | M8: =H87 -> 97 | N8: ConcPipe% | P8: 25
L9: 450PVC$/m | M9: =I87 -> 153 | N9: TrenchClear m | P9: 0.3
A11: Item | B11: RUN | C11: Length | D11: PIPE | E11: TYPE | F11: V/|| | G11: Depth | H11: Add | I11: Add | J11: OD | K11: Ground | M11: Trench | N11: %Prdtn | O11: DAY | P11: EXCAV | Q11: CALC | R11: PROD | S11: LAB&EQ | T11: PIPE | U11: TOTAL | V11: TOTAL $ | W11: TOTAL $ | X11: TOTAL $ | Y11: TOTAL $ | Z11: TOTAL $ | AA11: COST | AB11: TOTAL | AC11: Excav | AD11: Trench | AE11: TOTAL
A12: # | C12: =IF(P4=1,"METER","FEET") -> METER | D12: mm | E12: Class | F12: O/OO | G12: m | H12: Matrls $ | I12: L&E $ | J12: m | K12: Cover m | L12: calc. | M12: Width m | N12: Effcnt | O12: COST | P12: cm/m | Q12: PROD | R12: m/day | S12: $/m | T12: $/m | U12: $ PIPE | V12: Crshd St | W12: Granular | X12: Materials | Y12: Lab&Eq | Z12: TRUCKING | AA12: =IF(P4=1,"$/METER","$/FOOT") -> $/METER | AB12: COST | AC12: tcm | AD12: Lngth m | AE12: SALE
B13: STORM:
A14: 1 | J14: =0.00125*D14 -> 0 | K14: =IF(F14<2,F$4,G14-(1.12*D14*0.001)-F$5) -> 0.3 | L14: =(F14=2.1)*IF(G14<3.1,J14+3*S$6,J14+0.6+2*S$6+G14*0.05)+(F14=2.2)*IF(G14<3.1,J14+1.5*S$6+P$7/2,J14+0.3+S$6+G14*0.025) -> 0 | M14: =(F14=1.1)*IF((J14+2*P$9)<F$3,F$3,J14+2*P$9)+(F14=1.2)*(J14+P$9+P$7/2)+(F14=2.1)*IF(L14<F$3,F$3,L14)+(F14=2.2)*L14 -> 0 | N14: =P$3 -> 100 | O14: =F$6+HLOOKUP(G14,J$86:U$87,2)*F$7 -> 9000 | P14: =(M14*G14+(G14>1.219)*(F14=1.1)*(G14-1.22)^2*P$6+(F14=1.2)*(G14-1.22)^2/2*P$6)*(C14>0) -> 0 | Q14: =IF(C14=0,0,IF(TRUNC(F14)=1,HLOOKUP(G14,C$80:AC$81,2),HLOOKUP(G14,C$82:AC$83,2))*N14/100/IF((F14-TRUNC(F14))=0.2,P14*2,P14)) -> 0 | R14: =IF(Q14>F$8,F$8,Q14)*((F14=1.1)*1+(F14=1.2)*0.95+(F14=2.1)*0.95+(F14=2.2)*1) -> 0 | S14: =IF(C14=0,0,IF(OR(F14=1.2,F14=2.2),O14/R14/2,O14/R14)) -> 0 | T14: =IF(TRUNC(E14)>1,HLOOKUP(D14,C$86:I$87,2),IF(D14<=980,HLOOKUP(D14+10*(E14-1),B$74:AG$75,2),HLOOKUP(D14+10*(E14-1),B$76:AG$77,2))) -> #VALUE! | U14: =(IF(C14=0,0,IF(TRUNC(E14)=1,T14*C14*V$5,T14*C14*V$3)))*IF(P$4=1,1,1/3.28) -> 0 | V14: =((M14*0.6*J14+0.005)-PI()*J14^2/8)*C14*2*I$4*IF(P$4=1,1,1/3.28) -> 0 | W14: =(((0.5*J14+K14)*M14)-(PI()*J14^2/8))*C14*2*I$6*IF(P$4=1,1,1/3.28) -> 0 | X14: =H14+U14+V14+W14 -> 0 | Y14: =I14+S14*C14*IF(P$4=1,1,1/3.28) -> 0 | Z14: =((V14/I$4+W14/I$6)/2+PI()*J14^2/4*C14*IF(P$4=1,1,1/3.28))*I$7 -> 0 | AA14: =ROUND(IF(C14=0,0,(X14+Y14+Z14)/C14),2) -> 0 | AB14: =X14+Y14+Z14 -> 0 | AC14: =P14*C14*IF(P$4=1,1,1/3.28) -> 0 | AD14: =IF(C14=0,0,C14/((F14-TRUNC(F14))*10)*IF(P$4=1,1,1/3.28)) -> 0 | AE14: =AB14*$P$5 -> 0
A15: =A14+1 -> 2 | J15: =0.00125*D15 -> 0 | K15: =IF(F15<2,F$4,G15-(1.12*D15*0.001)-F$5) -> 0.3 | L15: =(F15=2.1)*IF(G15<3.1,J15+3*S$6,J15+0.6+2*S$6+G15*0.05)+(F15=2.2)*IF(G15<3.1,J15+1.5*S$6+P$7/2,J15+0.3+S$6+G15*0.025) -> 0 | M15: =(F15=1.1)*IF((J15+2*P$9)<F$3,F$3,J15+2*P$9)+(F15=1.2)*(J15+P$9+P$7/2)+(F15=2.1)*IF(L15<F$3,F$3,L15)+(F15=2.2)*L15 -> 0 | N15: =P$3 -> 100 | O15: =F$6+HLOOKUP(G15,J$86:U$87,2)*F$7 -> 9000 | P15: =(M15*G15+(G15>1.219)*(F15=1.1)*(G15-1.22)^2*P$6+(F15=1.2)*(G15-1.22)^2/2*P$6)*(C15>0) -> 0 | Q15: =IF(C15=0,0,IF(TRUNC(F15)=1,HLOOKUP(G15,C$80:AC$81,2),HLOOKUP(G15,C$82:AC$83,2))*N15/100/IF((F15-TRUNC(F15))=0.2,P15*2,P15)) -> 0 | R15: =IF(Q15>F$8,F$8,Q15)*((F15=1.1)*1+(F15=1.2)*0.95+(F15=2.1)*0.95+(F15=2.2)*1) -> 0 | S15: =IF(C15=0,0,IF(OR(F15=1.2,F15=2.2),O15/R15/2,O15/R15)) -> 0 | T15: =IF(TRUNC(E15)>1,HLOOKUP(D15,C$86:I$87,2),IF(D15<=980,HLOOKUP(D15+10*(E15-1),B$74:AG$75,2),HLOOKUP(D15+10*(E15-1),B$76:AG$77,2))) -> #VALUE! | U15: =(IF(C15=0,0,IF(TRUNC(E15)=1,T15*C15*V$5,T15*C15*V$3)))*IF(P$4=1,1,1/3.28) -> 0 | V15: =((M15*0.6*J15+0.005)-PI()*J15^2/8)*C15*2*I$4*IF(P$4=1,1,1/3.28) -> 0 | W15: =(((0.5*J15+K15)*M15)-(PI()*J15^2/8))*C15*2*I$6*IF(P$4=1,1,1/3.28) -> 0 | X15: =H15+U15+V15+W15 -> 0 | Y15: =I15+S15*C15*IF(P$4=1,1,1/3.28) -> 0 | Z15: =((V15/I$4+W15/I$6)/2+PI()*J15^2/4*C15*IF(P$4=1,1,1/3.28))*I$7 -> 0 | AA15: =ROUND(IF(C15=0,0,(X15+Y15+Z15)/C15),2) -> 0 | AB15: =X15+Y15+Z15 -> 0 | AC15: =P15*C15*IF(P$4=1,1,1/3.28) -> 0 | AD15: =IF(C15=0,0,C15/((F15-TRUNC(F15))*10)*IF(P$4=1,1,1/3.28)) -> 0 | AE15: =AB15*$P$5 -> 0
A16: =A15+1 -> 3 | J16: =0.00125*D16 -> 0 | K16: =IF(F16<2,F$4,G16-(1.12*D16*0.001)-F$5) -> 0.3 | L16: =(F16=2.1)*IF(G16<3.1,J16+3*S$6,J16+0.6+2*S$6+G16*0.05)+(F16=2.2)*IF(G16<3.1,J16+1.5*S$6+P$7/2,J16+0.3+S$6+G16*0.025) -> 0 | M16: =(F16=1.1)*IF((J16+2*P$9)<F$3,F$3,J16+2*P$9)+(F16=1.2)*(J16+P$9+P$7/2)+(F16=2.1)*IF(L16<F$3,F$3,L16)+(F16=2.2)*L16 -> 0 | N16: =P$3 -> 100 | O16: =F$6+HLOOKUP(G16,J$86:U$87,2)*F$7 -> 9000 | P16: =(M16*G16+(G16>1.219)*(F16=1.1)*(G16-1.22)^2*P$6+(F16=1.2)*(G16-1.22)^2/2*P$6)*(C16>0) -> 0 | Q16: =IF(C16=0,0,IF(TRUNC(F16)=1,HLOOKUP(G16,C$80:AC$81,2),HLOOKUP(G16,C$82:AC$83,2))*N16/100/IF((F16-TRUNC(F16))=0.2,P16*2,P16)) -> 0 | R16: =IF(Q16>F$8,F$8,Q16)*((F16=1.1)*1+(F16=1.2)*0.95+(F16=2.1)*0.95+(F16=2.2)*1) -> 0 | S16: =IF(C16=0,0,IF(OR(F16=1.2,F16=2.2),O16/R16/2,O16/R16)) -> 0 | T16: =IF(TRUNC(E16)>1,HLOOKUP(D16,C$86:I$87,2),IF(D16<=980,HLOOKUP(D16+10*(E16-1),B$74:AG$75,2),HLOOKUP(D16+10*(E16-1),B$76:AG$77,2))) -> #VALUE! | U16: =(IF(C16=0,0,IF(TRUNC(E16)=1,T16*C16*V$5,T16*C16*V$3)))*IF(P$4=1,1,1/3.28) -> 0 | V16: =((M16*0.6*J16+0.005)-PI()*J16^2/8)*C16*2*I$4*IF(P$4=1,1,1/3.28) -> 0 | W16: =(((0.5*J16+K16)*M16)-(PI()*J16^2/8))*C16*2*I$6*IF(P$4=1,1,1/3.28) -> 0 | X16: =H16+U16+V16+W16 -> 0 | Y16: =I16+S16*C16*IF(P$4=1,1,1/3.28) -> 0 | Z16: =((V16/I$4+W16/I$6)/2+PI()*J16^2/4*C16*IF(P$4=1,1,1/3.28))*I$7 -> 0 | AA16: =ROUND(IF(C16=0,0,(X16+Y16+Z16)/C16),2) -> 0 | AB16: =X16+Y16+Z16 -> 0 | AC16: =P16*C16*IF(P$4=1,1,1/3.28) -> 0 | AD16: =IF(C16=0,0,C16/((F16-TRUNC(F16))*10)*IF(P$4=1,1,1/3.28)) -> 0 | AE16: =AB16*$P$5 -> 0
A17: =A16+1 -> 4 | J17: =0.00125*D17 -> 0 | K17: =IF(F17<2,F$4,G17-(1.12*D17*0.001)-F$5) -> 0.3 | L17: =(F17=2.1)*IF(G17<3.1,J17+3*S$6,J17+0.6+2*S$6+G17*0.05)+(F17=2.2)*IF(G17<3.1,J17+1.5*S$6+P$7/2,J17+0.3+S$6+G17*0.025) -> 0 | M17: =(F17=1.1)*IF((J17+2*P$9)<F$3,F$3,J17+2*P$9)+(F17=1.2)*(J17+P$9+P$7/2)+(F17=2.1)*IF(L17<F$3,F$3,L17)+(F17=2.2)*L17 -> 0 | N17: =P$3 -> 100 | O17: =F$6+HLOOKUP(G17,J$86:U$87,2)*F$7 -> 9000 | P17: =(M17*G17+(G17>1.219)*(F17=1.1)*(G17-1.22)^2*P$6+(F17=1.2)*(G17-1.22)^2/2*P$6)*(C17>0) -> 0 | Q17: =IF(C17=0,0,IF(TRUNC(F17)=1,HLOOKUP(G17,C$80:AC$81,2),HLOOKUP(G17,C$82:AC$83,2))*N17/100/IF((F17-TRUNC(F17))=0.2,P17*2,P17)) -> 0 | R17: =IF(Q17>F$8,F$8,Q17)*((F17=1.1)*1+(F17=1.2)*0.95+(F17=2.1)*0.95+(F17=2.2)*1) -> 0 | S17: =IF(C17=0,0,IF(OR(F17=1.2,F17=2.2),O17/R17/2,O17/R17)) -> 0 | T17: =IF(TRUNC(E17)>1,HLOOKUP(D17,C$86:I$87,2),IF(D17<=980,HLOOKUP(D17+10*(E17-1),B$74:AG$75,2),HLOOKUP(D17+10*(E17-1),B$76:AG$77,2))) -> #VALUE! | U17: =(IF(C17=0,0,IF(TRUNC(E17)=1,T17*C17*V$5,T17*C17*V$3)))*IF(P$4=1,1,1/3.28) -> 0 | V17: =((M17*0.6*J17+0.005)-PI()*J17^2/8)*C17*2*I$4*IF(P$4=1,1,1/3.28) -> 0 | W17: =(((0.5*J17+K17)*M17)-(PI()*J17^2/8))*C17*2*I$6*IF(P$4=1,1,1/3.28) -> 0 | X17: =H17+U17+V17+W17 -> 0 | Y17: =I17+S17*C17*IF(P$4=1,1,1/3.28) -> 0 | Z17: =((V17/I$4+W17/I$6)/2+PI()*J17^2/4*C17*IF(P$4=1,1,1/3.28))*I$7 -> 0 | AA17: =ROUND(IF(C17=0,0,(X17+Y17+Z17)/C17),2) -> 0 | AB17: =X17+Y17+Z17 -> 0 | AC17: =P17*C17*IF(P$4=1,1,1/3.28) -> 0 | AD17: =IF(C17=0,0,C17/((F17-TRUNC(F17))*10)*IF(P$4=1,1,1/3.28)) -> 0 | AE17: =AB17*$P$5 -> 0
A18: =A17+1 -> 5 | J18: =0.00125*D18 -> 0 | K18: =IF(F18<2,F$4,G18-(1.12*D18*0.001)-F$5) -> 0.3 | L18: =(F18=2.1)*IF(G18<3.1,J18+3*S$6,J18+0.6+2*S$6+G18*0.05)+(F18=2.2)*IF(G18<3.1,J18+1.5*S$6+P$7/2,J18+0.3+S$6+G18*0.025) -> 0 | M18: =(F18=1.1)*IF((J18+2*P$9)<F$3,F$3,J18+2*P$9)+(F18=1.2)*(J18+P$9+P$7/2)+(F18=2.1)*IF(L18<F$3,F$3,L18)+(F18=2.2)*L18 -> 0 | N18: =P$3 -> 100 | O18: =F$6+HLOOKUP(G18,J$86:U$87,2)*F$7 -> 9000 | P18: =(M18*G18+(G18>1.219)*(F18=1.1)*(G18-1.22)^2*P$6+(F18=1.2)*(G18-1.22)^2/2*P$6)*(C18>0) -> 0 | Q18: =IF(C18=0,0,IF(TRUNC(F18)=1,HLOOKUP(G18,C$80:AC$81,2),HLOOKUP(G18,C$82:AC$83,2))*N18/100/IF((F18-TRUNC(F18))=0.2,P18*2,P18)) -> 0 | R18: =IF(Q18>F$8,F$8,Q18)*((F18=1.1)*1+(F18=1.2)*0.95+(F18=2.1)*0.95+(F18=2.2)*1) -> 0 | S18: =IF(C18=0,0,IF(OR(F18=1.2,F18=2.2),O18/R18/2,O18/R18)) -> 0 | T18: =IF(TRUNC(E18)>1,HLOOKUP(D18,C$86:I$87,2),IF(D18<=980,HLOOKUP(D18+10*(E18-1),B$74:AG$75,2),HLOOKUP(D18+10*(E18-1),B$76:AG$77,2))) -> #VALUE! | U18: =(IF(C18=0,0,IF(TRUNC(E18)=1,T18*C18*V$5,T18*C18*V$3)))*IF(P$4=1,1,1/3.28) -> 0 | V18: =((M18*0.6*J18+0.005)-PI()*J18^2/8)*C18*2*I$4*IF(P$4=1,1,1/3.28) -> 0 | W18: =(((0.5*J18+K18)*M18)-(PI()*J18^2/8))*C18*2*I$6*IF(P$4=1,1,1/3.28) -> 0 | X18: =H18+U18+V18+W18 -> 0 | Y18: =I18+S18*C18*IF(P$4=1,1,1/3.28) -> 0 | Z18: =((V18/I$4+W18/I$6)/2+PI()*J18^2/4*C18*IF(P$4=1,1,1/3.28))*I$7 -> 0 | AA18: =ROUND(IF(C18=0,0,(X18+Y18+Z18)/C18),2) -> 0 | AB18: =X18+Y18+Z18 -> 0 | AC18: =P18*C18*IF(P$4=1,1,1/3.28) -> 0 | AD18: =IF(C18=0,0,C18/((F18-TRUNC(F18))*10)*IF(P$4=1,1,1/3.28)) -> 0 | AE18: =AB18*$P$5 -> 0
A19: =A18+1 -> 6 | J19: =0.00125*D19 -> 0 | K19: =IF(F19<2,F$4,G19-(1.12*D19*0.001)-F$5) -> 0.3 | L19: =(F19=2.1)*IF(G19<3.1,J19+3*S$6,J19+0.6+2*S$6+G19*0.05)+(F19=2.2)*IF(G19<3.1,J19+1.5*S$6+P$7/2,J19+0.3+S$6+G19*0.025) -> 0 | M19: =(F19=1.1)*IF((J19+2*P$9)<F$3,F$3,J19+2*P$9)+(F19=1.2)*(J19+P$9+P$7/2)+(F19=2.1)*IF(L19<F$3,F$3,L19)+(F19=2.2)*L19 -> 0 | N19: =P$3 -> 100 | O19: =F$6+HLOOKUP(G19,J$86:U$87,2)*F$7 -> 9000 | P19: =(M19*G19+(G19>1.219)*(F19=1.1)*(G19-1.22)^2*P$6+(F19=1.2)*(G19-1.22)^2/2*P$6)*(C19>0) -> 0 | Q19: =IF(C19=0,0,IF(TRUNC(F19)=1,HLOOKUP(G19,C$80:AC$81,2),HLOOKUP(G19,C$82:AC$83,2))*N19/100/IF((F19-TRUNC(F19))=0.2,P19*2,P19)) -> 0 | R19: =IF(Q19>F$8,F$8,Q19)*((F19=1.1)*1+(F19=1.2)*0.95+(F19=2.1)*0.95+(F19=2.2)*1) -> 0 | S19: =IF(C19=0,0,IF(OR(F19=1.2,F19=2.2),O19/R19/2,O19/R19)) -> 0 | T19: =IF(TRUNC(E19)>1,HLOOKUP(D19,C$86:I$87,2),IF(D19<=980,HLOOKUP(D19+10*(E19-1),B$74:AG$75,2),HLOOKUP(D19+10*(E19-1),B$76:AG$77,2))) -> #VALUE! | U19: =(IF(C19=0,0,IF(TRUNC(E19)=1,T19*C19*V$5,T19*C19*V$3)))*IF(P$4=1,1,1/3.28) -> 0 | V19: =((M19*0.6*J19+0.005)-PI()*J19^2/8)*C19*2*I$4*IF(P$4=1,1,1/3.28) -> 0 | W19: =(((0.5*J19+K19)*M19)-(PI()*J19^2/8))*C19*2*I$6*IF(P$4=1,1,1/3.28) -> 0 | X19: =H19+U19+V19+W19 -> 0 | Y19: =I19+S19*C19*IF(P$4=1,1,1/3.28) -> 0 | Z19: =((V19/I$4+W19/I$6)/2+PI()*J19^2/4*C19*IF(P$4=1,1,1/3.28))*I$7 -> 0 | AA19: =ROUND(IF(C19=0,0,(X19+Y19+Z19)/C19),2) -> 0 | AB19: =X19+Y19+Z19 -> 0 | AC19: =P19*C19*IF(P$4=1,1,1/3.28) -> 0 | AD19: =IF(C19=0,0,C19/((F19-TRUNC(F19))*10)*IF(P$4=1,1,1/3.28)) -> 0 | AE19: =AB19*$P$5 -> 0
A20: =A19+1 -> 7 | J20: =0.00125*D20 -> 0 | K20: =IF(F20<2,F$4,G20-(1.12*D20*0.001)-F$5) -> 0.3 | L20: =(F20=2.1)*IF(G20<3.1,J20+3*S$6,J20+0.6+2*S$6+G20*0.05)+(F20=2.2)*IF(G20<3.1,J20+1.5*S$6+P$7/2,J20+0.3+S$6+G20*0.025) -> 0 | M20: =(F20=1.1)*IF((J20+2*P$9)<F$3,F$3,J20+2*P$9)+(F20=1.2)*(J20+P$9+P$7/2)+(F20=2.1)*IF(L20<F$3,F$3,L20)+(F20=2.2)*L20 -> 0 | N20: =P$3 -> 100 | O20: =F$6+HLOOKUP(G20,J$86:U$87,2)*F$7 -> 9000 | P20: =(M20*G20+(G20>1.219)*(F20=1.1)*(G20-1.22)^2*P$6+(F20=1.2)*(G20-1.22)^2/2*P$6)*(C20>0) -> 0 | Q20: =IF(C20=0,0,IF(TRUNC(F20)=1,HLOOKUP(G20,C$80:AC$81,2),HLOOKUP(G20,C$82:AC$83,2))*N20/100/IF((F20-TRUNC(F20))=0.2,P20*2,P20)) -> 0 | R20: =IF(Q20>F$8,F$8,Q20)*((F20=1.1)*1+(F20=1.2)*0.95+(F20=2.1)*0.95+(F20=2.2)*1) -> 0 | S20: =IF(C20=0,0,IF(OR(F20=1.2,F20=2.2),O20/R20/2,O20/R20)) -> 0 | T20: =IF(TRUNC(E20)>1,HLOOKUP(D20,C$86:I$87,2),IF(D20<=980,HLOOKUP(D20+10*(E20-1),B$74:AG$75,2),HLOOKUP(D20+10*(E20-1),B$76:AG$77,2))) -> #VALUE! | U20: =(IF(C20=0,0,IF(TRUNC(E20)=1,T20*C20*V$5,T20*C20*V$3)))*IF(P$4=1,1,1/3.28) -> 0 | V20: =((M20*0.6*J20+0.005)-PI()*J20^2/8)*C20*2*I$4*IF(P$4=1,1,1/3.28) -> 0 | W20: =(((0.5*J20+K20)*M20)-(PI()*J20^2/8))*C20*2*I$6*IF(P$4=1,1,1/3.28) -> 0 | X20: =H20+U20+V20+W20 -> 0 | Y20: =I20+S20*C20*IF(P$4=1,1,1/3.28) -> 0 | Z20: =((V20/I$4+W20/I$6)/2+PI()*J20^2/4*C20*IF(P$4=1,1,1/3.28))*I$7 -> 0 | AA20: =ROUND(IF(C20=0,0,(X20+Y20+Z20)/C20),2) -> 0 | AB20: =X20+Y20+Z20 -> 0 | AC20: =P20*C20*IF(P$4=1,1,1/3.28) -> 0 | AD20: =IF(C20=0,0,C20/((F20-TRUNC(F20))*10)*IF(P$4=1,1,1/3.28)) -> 0 | AE20: =AB20*$P$5 -> 0
A21: =A20+1 -> 8 | J21: =0.00125*D21 -> 0 | K21: =IF(F21<2,F$4,G21-(1.12*D21*0.001)-F$5) -> 0.3 | L21: =(F21=2.1)*IF(G21<3.1,J21+3*S$6,J21+0.6+2*S$6+G21*0.05)+(F21=2.2)*IF(G21<3.1,J21+1.5*S$6+P$7/2,J21+0.3+S$6+G21*0.025) -> 0 | M21: =(F21=1.1)*IF((J21+2*P$9)<F$3,F$3,J21+2*P$9)+(F21=1.2)*(J21+P$9+P$7/2)+(F21=2.1)*IF(L21<F$3,F$3,L21)+(F21=2.2)*L21 -> 0 | N21: =P$3 -> 100 | O21: =F$6+HLOOKUP(G21,J$86:U$87,2)*F$7 -> 9000 | P21: =(M21*G21+(G21>1.219)*(F21=1.1)*(G21-1.22)^2*P$6+(F21=1.2)*(G21-1.22)^2/2*P$6)*(C21>0) -> 0 | Q21: =IF(C21=0,0,IF(TRUNC(F21)=1,HLOOKUP(G21,C$80:AC$81,2),HLOOKUP(G21,C$82:AC$83,2))*N21/100/IF((F21-TRUNC(F21))=0.2,P21*2,P21)) -> 0 | R21: =IF(Q21>F$8,F$8,Q21)*((F21=1.1)*1+(F21=1.2)*0.95+(F21=2.1)*0.95+(F21=2.2)*1) -> 0 | S21: =IF(C21=0,0,IF(OR(F21=1.2,F21=2.2),O21/R21/2,O21/R21)) -> 0 | T21: =IF(TRUNC(E21)>1,HLOOKUP(D21,C$86:I$87,2),IF(D21<=980,HLOOKUP(D21+10*(E21-1),B$74:AG$75,2),HLOOKUP(D21+10*(E21-1),B$76:AG$77,2))) -> #VALUE! | U21: =(IF(C21=0,0,IF(TRUNC(E21)=1,T21*C21*V$5,T21*C21*V$3)))*IF(P$4=1,1,1/3.28) -> 0 | V21: =((M21*0.6*J21+0.005)-PI()*J21^2/8)*C21*2*I$4*IF(P$4=1,1,1/3.28) -> 0 | W21: =(((0.5*J21+K21)*M21)-(PI()*J21^2/8))*C21*2*I$6*IF(P$4=1,1,1/3.28) -> 0 | X21: =H21+U21+V21+W21 -> 0 | Y21: =I21+S21*C21*IF(P$4=1,1,1/3.28) -> 0 | Z21: =((V21/I$4+W21/I$6)/2+PI()*J21^2/4*C21*IF(P$4=1,1,1/3.28))*I$7 -> 0 | AA21: =ROUND(IF(C21=0,0,(X21+Y21+Z21)/C21),2) -> 0 | AB21: =X21+Y21+Z21 -> 0 | AC21: =P21*C21*IF(P$4=1,1,1/3.28) -> 0 | AD21: =IF(C21=0,0,C21/((F21-TRUNC(F21))*10)*IF(P$4=1,1,1/3.28)) -> 0 | AE21: =AB21*$P$5 -> 0
A22: =A21+1 -> 9 | J22: =0.00125*D22 -> 0 | K22: =IF(F22<2,F$4,G22-(1.12*D22*0.001)-F$5) -> 0.3 | L22: =(F22=2.1)*IF(G22<3.1,J22+3*S$6,J22+0.6+2*S$6+G22*0.05)+(F22=2.2)*IF(G22<3.1,J22+1.5*S$6+P$7/2,J22+0.3+S$6+G22*0.025) -> 0 | M22: =(F22=1.1)*IF((J22+2*P$9)<F$3,F$3,J22+2*P$9)+(F22=1.2)*(J22+P$9+P$7/2)+(F22=2.1)*IF(L22<F$3,F$3,L22)+(F22=2.2)*L22 -> 0 | N22: =P$3 -> 100 | O22: =F$6+HLOOKUP(G22,J$86:U$87,2)*F$7 -> 9000 | P22: =(M22*G22+(G22>1.219)*(F22=1.1)*(G22-1.22)^2*P$6+(F22=1.2)*(G22-1.22)^2/2*P$6)*(C22>0) -> 0 | Q22: =IF(C22=0,0,IF(TRUNC(F22)=1,HLOOKUP(G22,C$80:AC$81,2),HLOOKUP(G22,C$82:AC$83,2))*N22/100/IF((F22-TRUNC(F22))=0.2,P22*2,P22)) -> 0 | R22: =IF(Q22>F$8,F$8,Q22)*((F22=1.1)*1+(F22=1.2)*0.95+(F22=2.1)*0.95+(F22=2.2)*1) -> 0 | S22: =IF(C22=0,0,IF(OR(F22=1.2,F22=2.2),O22/R22/2,O22/R22)) -> 0 | T22: =IF(TRUNC(E22)>1,HLOOKUP(D22,C$86:I$87,2),IF(D22<=980,HLOOKUP(D22+10*(E22-1),B$74:AG$75,2),HLOOKUP(D22+10*(E22-1),B$76:AG$77,2))) -> #VALUE! | U22: =(IF(C22=0,0,IF(TRUNC(E22)=1,T22*C22*V$5,T22*C22*V$3)))*IF(P$4=1,1,1/3.28) -> 0 | V22: =((M22*0.6*J22+0.005)-PI()*J22^2/8)*C22*2*I$4*IF(P$4=1,1,1/3.28) -> 0 | W22: =(((0.5*J22+K22)*M22)-(PI()*J22^2/8))*C22*2*I$6*IF(P$4=1,1,1/3.28) -> 0 | X22: =H22+U22+V22+W22 -> 0 | Y22: =I22+S22*C22*IF(P$4=1,1,1/3.28) -> 0 | Z22: =((V22/I$4+W22/I$6)/2+PI()*J22^2/4*C22*IF(P$4=1,1,1/3.28))*I$7 -> 0 | AA22: =ROUND(IF(C22=0,0,(X22+Y22+Z22)/C22),2) -> 0 | AB22: =X22+Y22+Z22 -> 0 | AC22: =P22*C22*IF(P$4=1,1,1/3.28) -> 0 | AD22: =IF(C22=0,0,C22/((F22-TRUNC(F22))*10)*IF(P$4=1,1,1/3.28)) -> 0 | AE22: =AB22*$P$5 -> 0
A23: =A22+1 -> 10 | J23: =0.00125*D23 -> 0 | K23: =IF(F23<2,F$4,G23-(1.12*D23*0.001)-F$5) -> 0.3 | L23: =(F23=2.1)*IF(G23<3.1,J23+3*S$6,J23+0.6+2*S$6+G23*0.05)+(F23=2.2)*IF(G23<3.1,J23+1.5*S$6+P$7/2,J23+0.3+S$6+G23*0.025) -> 0 | M23: =(F23=1.1)*IF((J23+2*P$9)<F$3,F$3,J23+2*P$9)+(F23=1.2)*(J23+P$9+P$7/2)+(F23=2.1)*IF(L23<F$3,F$3,L23)+(F23=2.2)*L23 -> 0 | N23: =P$3 -> 100 | O23: =F$6+HLOOKUP(G23,J$86:U$87,2)*F$7 -> 9000 | P23: =(M23*G23+(G23>1.219)*(F23=1.1)*(G23-1.22)^2*P$6+(F23=1.2)*(G23-1.22)^2/2*P$6)*(C23>0) -> 0 | Q23: =IF(C23=0,0,IF(TRUNC(F23)=1,HLOOKUP(G23,C$80:AC$81,2),HLOOKUP(G23,C$82:AC$83,2))*N23/100/IF((F23-TRUNC(F23))=0.2,P23*2,P23)) -> 0 | R23: =IF(Q23>F$8,F$8,Q23)*((F23=1.1)*1+(F23=1.2)*0.95+(F23=2.1)*0.95+(F23=2.2)*1) -> 0 | S23: =IF(C23=0,0,IF(OR(F23=1.2,F23=2.2),O23/R23/2,O23/R23)) -> 0 | T23: =IF(TRUNC(E23)>1,HLOOKUP(D23,C$86:I$87,2),IF(D23<=980,HLOOKUP(D23+10*(E23-1),B$74:AG$75,2),HLOOKUP(D23+10*(E23-1),B$76:AG$77,2))) -> #VALUE! | U23: =(IF(C23=0,0,IF(TRUNC(E23)=1,T23*C23*V$5,T23*C23*V$3)))*IF(P$4=1,1,1/3.28) -> 0 | V23: =((M23*0.6*J23+0.005)-PI()*J23^2/8)*C23*2*I$4*IF(P$4=1,1,1/3.28) -> 0 | W23: =(((0.5*J23+K23)*M23)-(PI()*J23^2/8))*C23*2*I$6*IF(P$4=1,1,1/3.28) -> 0 | X23: =H23+U23+V23+W23 -> 0 | Y23: =I23+S23*C23*IF(P$4=1,1,1/3.28) -> 0 | Z23: =((V23/I$4+W23/I$6)/2+PI()*J23^2/4*C23*IF(P$4=1,1,1/3.28))*I$7 -> 0 | AA23: =ROUND(IF(C23=0,0,(X23+Y23+Z23)/C23),2) -> 0 | AB23: =X23+Y23+Z23 -> 0 | AC23: =P23*C23*IF(P$4=1,1,1/3.28) -> 0 | AD23: =IF(C23=0,0,C23/((F23-TRUNC(F23))*10)*IF(P$4=1,1,1/3.28)) -> 0 | AE23: =AB23*$P$5 -> 0
A24: =A23+1 -> 11 | J24: =0.00125*D24 -> 0 | K24: =IF(F24<2,F$4,G24-(1.12*D24*0.001)-F$5) -> 0.3 | L24: =(F24=2.1)*IF(G24<3.1,J24+3*S$6,J24+0.6+2*S$6+G24*0.05)+(F24=2.2)*IF(G24<3.1,J24+1.5*S$6+P$7/2,J24+0.3+S$6+G24*0.025) -> 0 | M24: =(F24=1.1)*IF((J24+2*P$9)<F$3,F$3,J24+2*P$9)+(F24=1.2)*(J24+P$9+P$7/2)+(F24=2.1)*IF(L24<F$3,F$3,L24)+(F24=2.2)*L24 -> 0 | N24: =P$3 -> 100 | O24: =F$6+HLOOKUP(G24,J$86:U$87,2)*F$7 -> 9000 | P24: =(M24*G24+(G24>1.219)*(F24=1.1)*(G24-1.22)^2*P$6+(F24=1.2)*(G24-1.22)^2/2*P$6)*(C24>0) -> 0 | Q24: =IF(C24=0,0,IF(TRUNC(F24)=1,HLOOKUP(G24,C$80:AC$81,2),HLOOKUP(G24,C$82:AC$83,2))*N24/100/IF((F24-TRUNC(F24))=0.2,P24*2,P24)) -> 0 | R24: =IF(Q24>F$8,F$8,Q24)*((F24=1.1)*1+(F24=1.2)*0.95+(F24=2.1)*0.95+(F24=2.2)*1) -> 0 | S24: =IF(C24=0,0,IF(OR(F24=1.2,F24=2.2),O24/R24/2,O24/R24)) -> 0 | T24: =IF(TRUNC(E24)>1,HLOOKUP(D24,C$86:I$87,2),IF(D24<=980,HLOOKUP(D24+10*(E24-1),B$74:AG$75,2),HLOOKUP(D24+10*(E24-1),B$76:AG$77,2))) -> #VALUE! | U24: =(IF(C24=0,0,IF(TRUNC(E24)=1,T24*C24*V$5,T24*C24*V$3)))*IF(P$4=1,1,1/3.28) -> 0 | V24: =((M24*0.6*J24+0.005)-PI()*J24^2/8)*C24*2*I$4*IF(P$4=1,1,1/3.28) -> 0 | W24: =(((0.5*J24+K24)*M24)-(PI()*J24^2/8))*C24*2*I$6*IF(P$4=1,1,1/3.28) -> 0 | X24: =H24+U24+V24+W24 -> 0 | Y24: =I24+S24*C24*IF(P$4=1,1,1/3.28) -> 0 | Z24: =((V24/I$4+W24/I$6)/2+PI()*J24^2/4*C24*IF(P$4=1,1,1/3.28))*I$7 -> 0 | AA24: =ROUND(IF(C24=0,0,(X24+Y24+Z24)/C24),2) -> 0 | AB24: =X24+Y24+Z24 -> 0 | AC24: =P24*C24*IF(P$4=1,1,1/3.28) -> 0 | AD24: =IF(C24=0,0,C24/((F24-TRUNC(F24))*10)*IF(P$4=1,1,1/3.28)) -> 0 | AE24: =AB24*$P$5 -> 0
A25: =A24+1 -> 12 | J25: =0.00125*D25 -> 0 | K25: =IF(F25<2,F$4,G25-(1.12*D25*0.001)-F$5) -> 0.3 | L25: =(F25=2.1)*IF(G25<3.1,J25+3*S$6,J25+0.6+2*S$6+G25*0.05)+(F25=2.2)*IF(G25<3.1,J25+1.5*S$6+P$7/2,J25+0.3+S$6+G25*0.025) -> 0 | M25: =(F25=1.1)*IF((J25+2*P$9)<F$3,F$3,J25+2*P$9)+(F25=1.2)*(J25+P$9+P$7/2)+(F25=2.1)*IF(L25<F$3,F$3,L25)+(F25=2.2)*L25 -> 0 | N25: =P$3 -> 100 | O25: =F$6+HLOOKUP(G25,J$86:U$87,2)*F$7 -> 9000 | P25: =(M25*G25+(G25>1.219)*(F25=1.1)*(G25-1.22)^2*P$6+(F25=1.2)*(G25-1.22)^2/2*P$6)*(C25>0) -> 0 | Q25: =IF(C25=0,0,IF(TRUNC(F25)=1,HLOOKUP(G25,C$80:AC$81,2),HLOOKUP(G25,C$82:AC$83,2))*N25/100/IF((F25-TRUNC(F25))=0.2,P25*2,P25)) -> 0 | R25: =IF(Q25>F$8,F$8,Q25)*((F25=1.1)*1+(F25=1.2)*0.95+(F25=2.1)*0.95+(F25=2.2)*1) -> 0 | S25: =IF(C25=0,0,IF(OR(F25=1.2,F25=2.2),O25/R25/2,O25/R25)) -> 0 | T25: =IF(TRUNC(E25)>1,HLOOKUP(D25,C$86:I$87,2),IF(D25<=980,HLOOKUP(D25+10*(E25-1),B$74:AG$75,2),HLOOKUP(D25+10*(E25-1),B$76:AG$77,2))) -> #VALUE! | U25: =(IF(C25=0,0,IF(TRUNC(E25)=1,T25*C25*V$5,T25*C25*V$3)))*IF(P$4=1,1,1/3.28) -> 0 | V25: =((M25*0.6*J25+0.005)-PI()*J25^2/8)*C25*2*I$4*IF(P$4=1,1,1/3.28) -> 0 | W25: =(((0.5*J25+K25)*M25)-(PI()*J25^2/8))*C25*2*I$6*IF(P$4=1,1,1/3.28) -> 0 | X25: =H25+U25+V25+W25 -> 0 | Y25: =I25+S25*C25*IF(P$4=1,1,1/3.28) -> 0 | Z25: =((V25/I$4+W25/I$6)/2+PI()*J25^2/4*C25*IF(P$4=1,1,1/3.28))*I$7 -> 0 | AA25: =ROUND(IF(C25=0,0,(X25+Y25+Z25)/C25),2) -> 0 | AB25: =X25+Y25+Z25 -> 0 | AC25: =P25*C25*IF(P$4=1,1,1/3.28) -> 0 | AD25: =IF(C25=0,0,C25/((F25-TRUNC(F25))*10)*IF(P$4=1,1,1/3.28)) -> 0 | AE25: =AB25*$P$5 -> 0
A26: =A25+1 -> 13 | J26: =0.00125*D26 -> 0 | K26: =IF(F26<2,F$4,G26-(1.12*D26*0.001)-F$5) -> 0.3 | L26: =(F26=2.1)*IF(G26<3.1,J26+3*S$6,J26+0.6+2*S$6+G26*0.05)+(F26=2.2)*IF(G26<3.1,J26+1.5*S$6+P$7/2,J26+0.3+S$6+G26*0.025) -> 0 | M26: =(F26=1.1)*IF((J26+2*P$9)<F$3,F$3,J26+2*P$9)+(F26=1.2)*(J26+P$9+P$7/2)+(F26=2.1)*IF(L26<F$3,F$3,L26)+(F26=2.2)*L26 -> 0 | N26: =P$3 -> 100 | O26: =F$6+HLOOKUP(G26,J$86:U$87,2)*F$7 -> 9000 | P26: =(M26*G26+(G26>1.219)*(F26=1.1)*(G26-1.22)^2*P$6+(F26=1.2)*(G26-1.22)^2/2*P$6)*(C26>0) -> 0 | Q26: =IF(C26=0,0,IF(TRUNC(F26)=1,HLOOKUP(G26,C$80:AC$81,2),HLOOKUP(G26,C$82:AC$83,2))*N26/100/IF((F26-TRUNC(F26))=0.2,P26*2,P26)) -> 0 | R26: =IF(Q26>F$8,F$8,Q26)*((F26=1.1)*1+(F26=1.2)*0.95+(F26=2.1)*0.95+(F26=2.2)*1) -> 0 | S26: =IF(C26=0,0,IF(OR(F26=1.2,F26=2.2),O26/R26/2,O26/R26)) -> 0 | T26: =IF(TRUNC(E26)>1,HLOOKUP(D26,C$86:I$87,2),IF(D26<=980,HLOOKUP(D26+10*(E26-1),B$74:AG$75,2),HLOOKUP(D26+10*(E26-1),B$76:AG$77,2))) -> #VALUE! | U26: =(IF(C26=0,0,IF(TRUNC(E26)=1,T26*C26*V$5,T26*C26*V$3)))*IF(P$4=1,1,1/3.28) -> 0 | V26: =((M26*0.6*J26+0.005)-PI()*J26^2/8)*C26*2*I$4*IF(P$4=1,1,1/3.28) -> 0 | W26: =(((0.5*J26+K26)*M26)-(PI()*J26^2/8))*C26*2*I$6*IF(P$4=1,1,1/3.28) -> 0 | X26: =H26+U26+V26+W26 -> 0 | Y26: =I26+S26*C26*IF(P$4=1,1,1/3.28) -> 0 | Z26: =((V26/I$4+W26/I$6)/2+PI()*J26^2/4*C26*IF(P$4=1,1,1/3.28))*I$7 -> 0 | AA26: =ROUND(IF(C26=0,0,(X26+Y26+Z26)/C26),2) -> 0 | AB26: =X26+Y26+Z26 -> 0 | AC26: =P26*C26*IF(P$4=1,1,1/3.28) -> 0 | AD26: =IF(C26=0,0,C26/((F26-TRUNC(F26))*10)*IF(P$4=1,1,1/3.28)) -> 0 | AE26: =AB26*$P$5 -> 0
... A51: =A50+1 -> 38 | J51: =0.00125*D51 -> 0 | K51: =IF(F51<2,F$4,G51-(1.12*D51*0.001)-F$5) -> 0.3 | L51: =(F51=2.1)*IF(G51<3.1,J51+3*S$6,J51+0.6+2*S$6+G51*0.05)+(F51=2.2)*IF(G51<3.1,J51+1.5*S$6+P$7/2,J51+0.3+S$6+G51*0.025) -> 0 | M51: =(F51=1.1)*IF((J51+2*P$9)<F$3,F$3,J51+2*P$9)+(F51=1.2)*(J51+P$9+P$7/2)+(F51=2.1)*IF(L51<F$3,F$3,L51)+(F51=2.2)*L51 -> 0 | N51: =P$3 -> 100 | O51: =F$6+HLOOKUP(G51,J$86:U$87,2)*F$7 -> 9000 | P51: =(M51*G51+(G51>1.219)*(F51=1.1)*(G51-1.22)^2*P$6+(F51=1.2)*(G51-1.22)^2/2*P$6)*(C51>0) -> 0 | Q51: =IF(C51=0,0,IF(TRUNC(F51)=1,HLOOKUP(G51,C$80:AC$81,2),HLOOKUP(G51,C$82:AC$83,2))*N51/100/IF((F51-TRUNC(F51))=0.2,P51*2,P51)) -> 0 | R51: =IF(Q51>F$8,F$8,Q51)*((F51=1.1)*1+(F51=1.2)*0.95+(F51=2.1)*0.95+(F51=2.2)*1) -> 0 | S51: =IF(C51=0,0,IF(OR(F51=1.2,F51=2.2),O51/R51/2,O51/R51)) -> 0 | T51: =IF(TRUNC(E51)>1,HLOOKUP(D51,C$86:I$87,2),IF(D51<=980,HLOOKUP(D51+10*(E51-1),B$74:AG$75,2),HLOOKUP(D51+10*(E51-1),B$76:AG$77,2))) -> #VALUE! | U51: =(IF(C51=0,0,IF(TRUNC(E51)=1,T51*C51*V$5,T51*C51*V$3)))*IF(P$4=1,1,1/3.28) -> 0 | V51: =((M51*0.6*J51+0.005)-PI()*J51^2/8)*C51*2*I$4*IF(P$4=1,1,1/3.28) -> 0 | W51: =(((0.5*J51+K51)*M51)-(PI()*J51^2/8))*C51*2*I$6*IF(P$4=1,1,1/3.28) -> 0 | X51: =H51+U51+V51+W51 -> 0 | Y51: =I51+S51*C51*IF(P$4=1,1,1/3.28) -> 0 | Z51: =((V51/I$4+W51/I$6)/2+PI()*J51^2/4*C51*IF(P$4=1,1,1/3.28))*I$7 -> 0 | AA51: =ROUND(IF(C51=0,0,(X51+Y51+Z51)/C51),2) -> 0 | AB51: =X51+Y51+Z51 -> 0 | AC51: =P51*C51*IF(P$4=1,1,1/3.28) -> 0 | AD51: =IF(C51=0,0,C51/((F51-TRUNC(F51))*10)*IF(P$4=1,1,1/3.28)) -> 0 | AE51: =AB51*$P$5 -> 0
A52: =A51+1 -> 39 | B52: VIDEO ($25/m) | H52: =15*C57 -> 0 | J52: =0.00125*D52 -> 0 | K52: =IF(F52<2,F$4,G52-(1.12*D52*0.001)-F$5) -> 0.3 | L52: =(F52=2.1)*IF(G52<3.1,J52+3*S$6,J52+0.6+2*S$6+G52*0.05)+(F52=2.2)*IF(G52<3.1,J52+1.5*S$6+P$7/2,J52+0.3+S$6+G52*0.025) -> 0 | M52: =(F52=1.1)*IF((J52+2*P$9)<F$3,F$3,J52+2*P$9)+(F52=1.2)*(J52+P$9+P$7/2)+(F52=2.1)*IF(L52<F$3,F$3,L52)+(F52=2.2)*L52 -> 0 | N52: =P$3 -> 100 | O52: =F$6+HLOOKUP(G52,J$86:U$87,2)*F$7 -> 9000 | P52: =(M52*G52+(G52>1.219)*(F52=1.1)*(G52-1.22)^2*P$6+(F52=1.2)*(G52-1.22)^2/2*P$6)*(C52>0) -> 0 | Q52: =IF(C52=0,0,IF(TRUNC(F52)=1,HLOOKUP(G52,C$80:AC$81,2),HLOOKUP(G52,C$82:AC$83,2))*N52/100/IF((F52-TRUNC(F52))=0.2,P52*2,P52)) -> 0 | R52: =IF(Q52>F$8,F$8,Q52)*((F52=1.1)*1+(F52=1.2)*0.95+(F52=2.1)*0.95+(F52=2.2)*1) -> 0 | S52: =IF(C52=0,0,IF(OR(F52=1.2,F52=2.2),O52/R52/2,O52/R52)) -> 0 | T52: =IF(TRUNC(E52)>1,HLOOKUP(D52,C$86:I$87,2),IF(D52<=980,HLOOKUP(D52+10*(E52-1),B$74:AG$75,2),HLOOKUP(D52+10*(E52-1),B$76:AG$77,2))) -> #VALUE! | U52: =(IF(C52=0,0,IF(TRUNC(E52)=1,T52*C52*V$5,T52*C52*V$3)))*IF(P$4=1,1,1/3.28) -> 0 | V52: =((M52*0.6*J52+0.005)-PI()*J52^2/8)*C52*2*I$4*IF(P$4=1,1,1/3.28) -> 0 | W52: =(((0.5*J52+K52)*M52)-(PI()*J52^2/8))*C52*2*I$6*IF(P$4=1,1,1/3.28) -> 0 | X52: =H52+U52+V52+W52 -> 0 | Y52: =I52+S52*C52*IF(P$4=1,1,1/3.28) -> 0 | Z52: =((V52/I$4+W52/I$6)/2+PI()*J52^2/4*C52*IF(P$4=1,1,1/3.28))*I$7 -> 0 | AA52: =ROUND(IF(C52=0,0,(X52+Y52+Z52)/C52),2) -> 0 | AB52: =X52+Y52+Z52 -> 0 | AC52: =P52*C52*IF(P$4=1,1,1/3.28) -> 0 | AD52: =IF(C52=0,0,C52/((F52-TRUNC(F52))*10)*IF(P$4=1,1,1/3.28)) -> 0 | AE52: =AB52*$P$5 -> 0
A53: =A52+1 -> 40 | B53: LAYOUT | H53: 5000 | J53: =0.00125*D53 -> 0 | K53: =IF(F53<2,F$4,G53-(1.12*D53*0.001)-F$5) -> 0.3 | L53: =(F53=2.1)*IF(G53<3.1,J53+3*S$6,J53+0.6+2*S$6+G53*0.05)+(F53=2.2)*IF(G53<3.1,J53+1.5*S$6+P$7/2,J53+0.3+S$6+G53*0.025) -> 0 | M53: =(F53=1.1)*IF((J53+2*P$9)<F$3,F$3,J53+2*P$9)+(F53=1.2)*(J53+P$9+P$7/2)+(F53=2.1)*IF(L53<F$3,F$3,L53)+(F53=2.2)*L53 -> 0 | N53: =P$3 -> 100 | O53: =F$6+HLOOKUP(G53,J$86:U$87,2)*F$7 -> 9000 | P53: =(M53*G53+(G53>1.219)*(F53=1.1)*(G53-1.22)^2*P$6+(F53=1.2)*(G53-1.22)^2/2*P$6)*(C53>0) -> 0 | Q53: =IF(C53=0,0,IF(TRUNC(F53)=1,HLOOKUP(G53,C$80:AC$81,2),HLOOKUP(G53,C$82:AC$83,2))*N53/100/IF((F53-TRUNC(F53))=0.2,P53*2,P53)) -> 0 | R53: =IF(Q53>F$8,F$8,Q53)*((F53=1.1)*1+(F53=1.2)*0.95+(F53=2.1)*0.95+(F53=2.2)*1) -> 0 | S53: =IF(C53=0,0,IF(OR(F53=1.2,F53=2.2),O53/R53/2,O53/R53)) -> 0 | T53: =IF(TRUNC(E53)>1,HLOOKUP(D53,C$86:I$87,2),IF(D53<=980,HLOOKUP(D53+10*(E53-1),B$74:AG$75,2),HLOOKUP(D53+10*(E53-1),B$76:AG$77,2))) -> #VALUE! | U53: =(IF(C53=0,0,IF(TRUNC(E53)=1,T53*C53*V$5,T53*C53*V$3)))*IF(P$4=1,1,1/3.28) -> 0 | V53: =((M53*0.6*J53+0.005)-PI()*J53^2/8)*C53*2*I$4*IF(P$4=1,1,1/3.28) -> 0 | W53: =(((0.5*J53+K53)*M53)-(PI()*J53^2/8))*C53*2*I$6*IF(P$4=1,1,1/3.28) -> 0 | X53: =H53+U53+V53+W53 -> 5000 | Y53: =I53+S53*C53*IF(P$4=1,1,1/3.28) -> 0 | Z53: =((V53/I$4+W53/I$6)/2+PI()*J53^2/4*C53*IF(P$4=1,1,1/3.28))*I$7 -> 0 | AA53: =ROUND(IF(C53=0,0,(X53+Y53+Z53)/C53),2) -> 0 | AB53: =X53+Y53+Z53 -> 5000 | AC53: =P53*C53*IF(P$4=1,1,1/3.28) -> 0 | AD53: =IF(C53=0,0,C53/((F53-TRUNC(F53))*10)*IF(P$4=1,1,1/3.28)) -> 0 | AE53: =AB53*$P$5 -> 5500
A54: =A53+1 -> 41 | B54: AS BUILT | H54: 5000 | J54: =0.00125*D54 -> 0 | K54: =IF(F54<2,F$4,G54-(1.12*D54*0.001)-F$5) -> 0.3 | L54: =(F54=2.1)*IF(G54<3.1,J54+3*S$6,J54+0.6+2*S$6+G54*0.05)+(F54=2.2)*IF(G54<3.1,J54+1.5*S$6+P$7/2,J54+0.3+S$6+G54*0.025) -> 0 | M54: =(F54=1.1)*IF((J54+2*P$9)<F$3,F$3,J54+2*P$9)+(F54=1.2)*(J54+P$9+P$7/2)+(F54=2.1)*IF(L54<F$3,F$3,L54)+(F54=2.2)*L54 -> 0 | N54: =P$3 -> 100 | O54: =F$6+HLOOKUP(G54,J$86:U$87,2)*F$7 -> 9000 | P54: =(M54*G54+(G54>1.219)*(F54=1.1)*(G54-1.22)^2*P$6+(F54=1.2)*(G54-1.22)^2/2*P$6)*(C54>0) -> 0 | Q54: =IF(C54=0,0,IF(TRUNC(F54)=1,HLOOKUP(G54,C$80:AC$81,2),HLOOKUP(G54,C$82:AC$83,2))*N54/100/IF((F54-TRUNC(F54))=0.2,P54*2,P54)) -> 0 | R54: =IF(Q54>F$8,F$8,Q54)*((F54=1.1)*1+(F54=1.2)*0.95+(F54=2.1)*0.95+(F54=2.2)*1) -> 0 | S54: =IF(C54=0,0,IF(OR(F54=1.2,F54=2.2),O54/R54/2,O54/R54)) -> 0 | T54: =IF(TRUNC(E54)>1,HLOOKUP(D54,C$86:I$87,2),IF(D54<=980,HLOOKUP(D54+10*(E54-1),B$74:AG$75,2),HLOOKUP(D54+10*(E54-1),B$76:AG$77,2))) -> #VALUE! | U54: =(IF(C54=0,0,IF(TRUNC(E54)=1,T54*C54*V$5,T54*C54*V$3)))*IF(P$4=1,1,1/3.28) -> 0 | V54: =((M54*0.6*J54+0.005)-PI()*J54^2/8)*C54*2*I$4*IF(P$4=1,1,1/3.28) -> 0 | W54: =(((0.5*J54+K54)*M54)-(PI()*J54^2/8))*C54*2*I$6*IF(P$4=1,1,1/3.28) -> 0 | X54: =H54+U54+V54+W54 -> 5000 | Y54: =I54+S54*C54*IF(P$4=1,1,1/3.28) -> 0 | Z54: =((V54/I$4+W54/I$6)/2+PI()*J54^2/4*C54*IF(P$4=1,1,1/3.28))*I$7 -> 0 | AA54: =ROUND(IF(C54=0,0,(X54+Y54+Z54)/C54),2) -> 0 | AB54: =X54+Y54+Z54 -> 5000 | AC54: =P54*C54*IF(P$4=1,1,1/3.28) -> 0 | AD54: =IF(C54=0,0,C54/((F54-TRUNC(F54))*10)*IF(P$4=1,1,1/3.28)) -> 0 | AE54: =AB54*$P$5 -> 5500
B56: TOTAL COSTS | H56: =SUM(H13:H55) -> 10000 | I56: =SUM(I13:I55) -> 0 | U56: =SUM(U14:U54) -> 0 | V56: =SUM(V13:V54) -> 0 | W56: =SUM(W13:W55) -> 0 | X56: =SUM(X14:X54) -> 10000 | Y56: =SUM(Y13:Y55) -> 0 | Z56: =SUM(Z14:Z54) -> 0 | AB56: =SUM(AB14:AB54) -> 10000 | AE56: =SUM(AE14:AE54) -> 11000
B57: TOTAL QUANTITIES | C57: =SUM(C14:C54) -> 0 | D57: =IF(P4=1,"METERS","FEET") -> METERS | V57: =V56/I$4 -> 0 | W57: =W56/I$6 -> 0 | Z57: =Z56/I$7 -> 0 | AC57: =SUM(AC13:AC54) -> 0 | AD57: =SUM(AD13:AD54) -> 0
B60: $ Concrete Pipe | C60: =SUMIFS(U14:U54,E14:E54,">1",E14:E54,"<2") -> 0 | H60: Total cm Excavation | I60: =AC57 -> 0 | N60: Avg L&E $/cm | O60: =IF(AC57=0,0,Y56/AC57) -> 0 | Y60: TOTALS | Z60: $COST | AA60: MARGIN | AB60: TOTAL SALE $
B61: $ Plastic Pipe | C61: =SUMIFS(U14:U54,E14:E54,">=2",E14:E54,"<3") -> 0 | H61: Total Meters Trench | I61: =AD57 -> 0 | N61: Days @ AvDCst | O61: =Y56/F6 -> 0
B62: $Crushed Stone (cst) | C62: =V56 -> 0 | H62: Total Feet Trench | I62: =AD57*3.28 -> 0 | N62: Avg DR cm/day | O62: =IF(O61=0,0,AC57/O61) -> 0 | Y62: MATERIALS: | Z62: =X56 -> 10000 | AA62: =(P5-TRUNC(P5))*Z62 -> 1000 | AB62: =Z62+AA62 -> 11000
B63: $ Additional Materials | C63: =H56 -> 10000 | H63: Total Meters Pipe | I63: =IF(P4=1,C57,C57*1/3.28) -> 0 | N63: Trench m/day | O63: =IF(O61=0,0,I61/O61) -> 0 | Y63: LAB&EQUIP: | Z63: =Y56 -> 0 | AA63: =(P5-TRUNC(P5))*Z63 -> 0 | AB63: =Z63+AA63 -> 0
B64: $ Total Materials | C64: =X56 -> 10000 | H64: Total Feet Pipe | I64: =IF(P4=0,C57,C57*3.28) -> 0 | N64: Trench ft/day | O64: =O63*3.28 -> 0 | Y64: TRUCKING: | Z64: =Z56 -> 0 | AA64: =(P5-TRUNC(P5))*Z64 -> 0 | AB64: =Z64+AA64 -> 0
B65: $ Labour @ 70% | C65: =0.7*Y56 -> 0 | H65: PerCent Materials | I65: =IF(AB56=0,0,X56/AB56*100) -> 100 | N65: Pipe m/day | O65: =IF(O61=0,0,I63/O61) -> 0
B66: $ Equipment 30% | C66: =0.3*Y56 -> 0 | H66: PerCent Lab & Equ | I66: =IF(AB56=0,0,Y56/AB56*100) -> 0 | N66: Pipe ft/day | O66: =IF(O61=0,0,I64/O61) -> 0
B67: $ Total L & E | C67: =Y56 -> 0 | H67: PerCent Trucking | I67: =IF(I65=0,0,100-I65-I66) -> 0 | N67: $ m pipe/day | O67: =IF(I63=0,0,Y56/I63) -> 0 | Y67: BID PRICE | Z67: =SUM(Z61:Z65) -> 10000 | AA67: =SUM(AA61:AA65) -> 1000 | AB67: =SUM(AB61:AB65) -> 11000
B68: $ Trucking | C68: =Z56 -> 0 | N68: $ m trench/day | O68: =IF(I61=0,0,Y56/I61) -> 0
A73: LOOKUP TABLES FOR CONCRETE PIPE FEB 2020
A74: C.P. | B74: 151 | C74: 201 | D74: 251 | E74: 301 | F74: 302 | G74: 376 | H74: 377 | I74: 451 | J74: 452 | K74: 455 | L74: 527 | M74: 529 | N74: 530 | O74: 602 | P74: 604 | Q74: 605 | R74: 677 | S74: 679 | T74: 680 | U74: 752 | V74: 754 | W74: 755 | X74: 827 | Y74: 829 | Z74: 830 | AA74: 902 | AB74: 904 | AC74: 905 | AD74: 977 | AE74: 978 | AF74: 979 | AG74: 980
A75: $/M | B75: 14.9 | C75: 22.6 | D75: 29.3 | E75: 95.1 | F75: 95.1 | G75: 117.2 | H75: 117.2 | I75: 120.8 | J75: 120.8 | K75: 151 | L75: 131.7 | M75: 153.8 | N75: 181.7 | O75: 177.3 | P75: 203.7 | Q75: 239.6 | R75: 271.8 | S75: 309.5 | T75: 362.5 | U75: 358.2 | V75: 409.5 | W75: 478.7 | X75: 415.6 | Y75: 528.6 | Z75: 555.3 | AA75: 498.6 | AB75: 570.4 | AC75: 665.9 | AD75: 547 | AE75: 575.9 | AF75: 655.4 | AG75: 767
A76: 42064 | B76: 1052 | C76: 1053 | D76: 1054 | E76: 1055 | F76: 1202 | G76: 1203 | H76: 1204 | I76: 1205 | J76: 1352 | K76: 1353 | L76: 1354 | M76: 1355 | N76: 1502 | O76: 1503 | P76: 1504 | Q76: 1505 | R76: 1652 | S76: 1653 | T76: 1654 | U76: 1655 | V76: 1802 | W76: 1803 | X76: 1804 | Y76: 1805 | Z76: 1952 | AA76: 1953 | AB76: 1954 | AC76: 1955 | AD76: 2102 | AE76: 2103 | AF76: 2104 | AG76: 2105
A77: LKUP | B77: 626.5 | C77: 657.9 | D77: 753.4 | E77: 877.6 | F77: 785.2 | G77: 824.8 | H77: 943.7 | I77: 1099.5 | J77: 1009.8 | K77: 1060.3 | L77: 1212.9 | M77: 1412.6 | N77: 1235.2 | O77: 1296.3 | P77: 1482.1 | Q77: 1729.1 | R77: 1479.1 | S77: 1554.2 | T77: 1776.4 | U77: 2071.1 | V77: 1787.3 | W77: 1879.2 | X77: 2145.4 | Y77: 2503.4 | Z77: 2072.8 | AA77: 2178.9 | AB77: 2486.9 | AC77: 2903.1 | AD77: 2378.6 | AE77: 2495 | AF77: 2853.5 | AG77: 3328.1
A79: LOOKUP TABLE FOR DIG RATES
A80: Open Cut Depth m | C80: 1 | D80: 1.2 | E80: 1.4 | F80: 1.6 | G80: 1.8 | H80: 2 | I80: 2.2 | J80: 2.3 | K80: 2.4 | L80: 2.6 | M80: 2.8 | N80: 3 | O80: 3.2 | P80: 3.4 | Q80: 3.6 | R80: 3.8 | S80: 4 | T80: 4.2 | U80: 4.4 | V80: 4.6 | W80: 4.8 | X80: 5 | Y80: 5.2 | Z80: 5.4 | AA80: 5.6 | AB80: 5.8 | AC80: 6
A81: LU Table DigRate cm/min | C81: 120 | D81: 135 | E81: 160 | F81: 180 | G81: 240 | H81: 270 | I81: 325 | J81: 350 | K81: 380 | L81: 440 | M81: 500 | N81: 550 | O81: 605 | P81: 665 | Q81: 710 | R81: 760 | S81: 800 | T81: 850 | U81: 900 | V81: 920 | W81: 925 | X81: 925 | Y81: 920 | Z81: 900 | AA81: 830 | AB81: 750 | AC81: 710
A82: Str Cut Depth m | C82: 1 | D82: 1.2 | E82: 1.4 | F82: 1.6 | G82: 1.8 | H82: 2 | I82: 2.2 | J82: 2.3 | K82: 2.4 | L82: 2.6 | M82: 2.8 | N82: 3 | O82: 3.2 | P82: 3.4 | Q82: 3.6 | R82: 3.8 | S82: 4 | T82: 4.2 | U82: 4.4 | V82: 4.6 | W82: 4.8 | X82: 5 | Y82: 5.2 | Z82: 5.4 | AA82: 5.6 | AB82: 5.8 | AC82: 6
A83: LU Table DigRate cm/min | C83: 74 | D83: 98 | E83: 119 | F83: 145 | G83: 165 | H83: 175 | I83: 180 | J83: 183 | K83: 185 | L83: 190 | M83: 195 | N83: 200 | O83: 203 | P83: 203 | Q83: 203 | R83: 203 | S83: 203 | T83: 203 | U83: 203 | V83: 203 | W83: 203 | X83: 203 | Y83: 203 | Z83: 203 | AA83: 203 | AB83: 203 | AC83: 196
A85: LOOKUP TABLE FOR PVC PIPES
A86: Non CP | C86: 100 | D86: 150 | E86: 200 | F86: 250 | G86: 300 | H86: 375 | I86: 450 | J86: 0 | K86: 0 | L86: 2.4 | M86: 3 | N86: 3.7 | O86: 4.3 | P86: 4.9 | Q86: 5.5 | R86: 6.1 | S86: 6.7 | T86: 7.3 | U86: 7.6
A87: $/m | B87: pvc-April/2011 | C87: 12 | D87: 24 | E87: 34 | F87: 51 | G87: 73 | H87: 97 | I87: 153 | J87: 0 | K87: 0 | L87: 0.1 | M87: 0.2 | N87: 0.4 | O87: 0.7 | P87: 0.9 | Q87: 1.2 | R87: 1.5 | S87: 1.6 | T87: 1.8 | U87: 2
C88: DR28 | D88: DR28 | E88: DR35 | F88: DR35 | G88: DR35 | H88: DR35 | I88: DR35

Sheet WATERMAIN (1)
D1: TOPSITE CONTRACTING | G1: WATERMAIN ESTIMATE | X1: =B2 -> 0
A2: ='MANHOLES (1)'!A2 -> PROJECT | B2: ='MANHOLES (1)'!B2 -> 0 | X2: =G1 -> WATERMAIN ESTIMATE
B3: ='MANHOLES (1)'!B3 -> 0 | D3: Min Trench W | F3: 1.2 | G3: $/ImpTonScrng | I3: 22 | K3: 100 C900 | L3: 32 | N3: %Efficiency | O3: 100 | T3: ProvTax | U3: 1
D4: Pipe Cover | F4: 0.3 | G4: $/MtneStone | I4: 35 | K4: 150 C900 | L4: 51 | N4: M/Imp (1/0) | O4: 1 | Q4: Precast % | R4: 5 | T4: FedTax | U4: 1
A5: ='MANHOLES (1)'!A5 -> Date: | B5: ='MANHOLES (1)'!B5 -> 0 | D5: M-Fin Grade | F5: 0 | G5: $/ImpTon Gran | I5: 10 | K5: 200 C900 | L5: 84 | N5: Margin Fctr | O5: ='MANHOLES (1)'!F6 -> 1.1 | T5: CP Factor | U5: 1.02078
D6: Daycost$/Day | F6: 9000 | G6: $/MtneGran | I6: 30 | K6: 250 C900 | L6: 121 | N6: OpnCtFctr | O6: 0.9 | U6: 1.07749
D7: $Xtra/Day | F7: 300 | G7: $Trucking/cm | I7: ='MANHOLES (1)'!F3 -> 10 | K7: 300 C900 | L7: 194 | N7: DualTrSep M | O7: 1 | Q7: $Moduloc/m | R7: 620 | V7: * Trench Width dual 1/2 actual
D8: Prdctn M/Day | F8: 65 | G8: PeelRegionCvr | I8: 0 | K8: Conc$/CM | L8: 250 | N8: TrenClear M | O8: 0.15
A10: ITM | B10: WATERMAIN | C10: LENGTH | D10: PIPE D | E10: PIPE$/m | F10: OC/SC | G10: ADDTNL | H10: ADDTNL | I10: PROD | J10: AVERAGE | K10: GRNLR | L10: $/DAY | M10: LAB&EQP | N10: TRENCH* | O10: EXCAV | P10: TOTAL | Q10: LENGTH | R10: TOTAL | S10: TOTAL | T10: TOTAL | U10: TOTAL | V10: TOTAL $ | W10: TOTAL $ | X10: UNITCOST | Y10: TOTAL
A11: # | B11: SIZE & TYPE | C11: =IF(O4=1,"METERS","FEET") -> METERS | D11: mm | E11: cw FedX | F11: S/D | G11: MATRL $ | H11: L&E $ | I11: m/DAY | J11: COVER m | K11: COVER m | L11: COST | M11: $/m | N11: WIDTH m | O11: cm/m | P11: EXC cm | Q11: TRNCH m | R11: $ PIPE | S11: $ SCRNGS | T11: $ GRANLR | U11: $ MATRL | V11: LAB&EQP | W11: TRUCKING | X11: =IF(O4=1,"$/METER","$/FOOT") -> $/METER | Y11: COST
A13: 1 | E13: =(D13=100)*L$3+(D13=150)*L$4+(D13=200)*L$5+(D13=250)*L$6+(D13=300)*L$7 -> 0 | F13: 1.1 | I13: =IF(F13>2,F$8*0.9,F$8)*(O$3/100) -> 65 | J13: 1.8 | K13: =(TRUNC(F13)=2)*((I$8=0)*IF(F$4=0,0,J13-F$5)+(I$8>0)*(J13-I$8-F$5))+(TRUNC(F13)=1)*((I$8=0)*IF(F$4=0,0,F$4)) -> 0.3 | L13: =IF(F13>2,F$6+0.5*F$7,F$6) -> 9000 | M13: =(C13>0)*L13/I13*IF(OR(F13=1.2,F13=2.2),0.6,1) -> 0 | N13: =(F13=1.1)*F$3+(F13=1.2)*(2*1.25*D13/1000+2*O$8+O$7)/2+(F13=2.1)*(F$3+0.3)+(F13=2.2)*(2*1.25*D13/1000+4*O$8+O$7)/2 -> 1.2 | O13: =((N13*(J13+1.25*D13/1000+0.1)+(TRUNC(F13)=1)*(J13-0.9)^2*O$6)*IF(F13-TRUNC(F13)=0.2,0.5,1))*(C13>0) -> 0 | P13: =O13*C13*IF(O$4=1,1,1/3.28) -> 0 | Q13: =IF(F13-TRUNC(F13)=0.2,0.5,1)*C13*IF(O$4=1,1,1/3.28) -> 0 | R13: =C13*E13*U$3*IF(O$4=1,1,1/3.28) -> 0 | S13: =IF(I$8>0,N13*(0.1+0.00125*D13+I$8)-PI()*(D13*0.00125)^2/4,0)*2*I4*C13*IF(O$4=2,1,1/3.28) -> 0 | T13: =IF(K13=0,0,1)*IF(AND(I$8=0,K13>0),N13*(0.1+0.00125*D13+K13)-PI()*(D13*0.00125)^2/4,N13*K13)*2*I$6*C13*IF(O$4=1,1,1/3.28) -> 0 | U13: =G13+R13+S13+T13 -> 0 | V13: =H13+C13*M13*IF(O$4=1,1,1/3.28) -> 0 | W13: =((IF(S13=0,0,S13/I$4)+IF(T13=0,0,T13/I$6))/2+PI()*(D13*0.00125)^2/4*C13*IF(O$4=1,1,1/3.28))*I$7 -> 0 | X13: =IF(C13=0,0,(U13+V13+W13)/C13) -> 0 | Y13: =U13+V13+W13 -> 0
A14: 2 | E14: =(D14=100)*L$3+(D14=150)*L$4+(D14=200)*L$5+(D14=250)*L$6+(D14=300)*L$7 -> 0 | F14: 1.1 | I14: =IF(F14>2,F$8*0.9,F$8)*(O$3/100) -> 65 | J14: 1.8 | K14: =(TRUNC(F14)=2)*((I$8=0)*IF(F$4=0,0,J14-F$5)+(I$8>0)*(J14-I$8-F$5))+(TRUNC(F14)=1)*((I$8=0)*IF(F$4=0,0,F$4)) -> 0.3 | L14: =IF(F14>2,F$6+0.5*F$7,F$6) -> 9000 | M14: =(C14>0)*L14/I14*IF(OR(F14=1.2,F14=2.2),0.6,1) -> 0 | N14: =(F14=1.1)*F$3+(F14=1.2)*(2*1.25*D14/1000+2*O$8+O$7)/2+(F14=2.1)*(F$3+0.3)+(F14=2.2)*(2*1.25*D14/1000+4*O$8+O$7)/2 -> 1.2 | O14: =((N14*(J14+1.25*D14/1000+0.1)+(TRUNC(F14)=1)*(J14-0.9)^2*O$6)*IF(F14-TRUNC(F14)=0.2,0.5,1))*(C14>0) -> 0 | P14: =O14*C14*IF(O$4=1,1,1/3.28) -> 0 | Q14: =IF(F14-TRUNC(F14)=0.2,0.5,1)*C14*IF(O$4=1,1,1/3.28) -> 0 | R14: =C14*E14*U$3*IF(O$4=1,1,1/3.28) -> 0 | S14: =IF(I$8>0,N14*(0.1+0.00125*D14+I$8)-PI()*(D14*0.00125)^2/4,0)*2*I5*C14*IF(O$4=2,1,1/3.28) -> 0 | T14: =IF(K14=0,0,1)*IF(AND(I$8=0,K14>0),N14*(0.1+0.00125*D14+K14)-PI()*(D14*0.00125)^2/4,N14*K14)*2*I$6*C14*IF(O$4=1,1,1/3.28) -> 0 | U14: =G14+R14+S14+T14 -> 0 | V14: =H14+C14*M14*IF(O$4=1,1,1/3.28) -> 0 | W14: =((IF(S14=0,0,S14/I$4)+IF(T14=0,0,T14/I$6))/2+PI()*(D14*0.00125)^2/4*C14*IF(O$4=1,1,1/3.28))*I$7 -> 0 | X14: =IF(C14=0,0,(U14+V14+W14)/C14) -> 0 | Y14: =U14+V14+W14 -> 0
A15: 3 | E15: =(D15=100)*L$3+(D15=150)*L$4+(D15=200)*L$5+(D15=250)*L$6+(D15=300)*L$7 -> 0 | F15: 1.1 | I15: =IF(F15>2,F$8*0.9,F$8)*(O$3/100) -> 65 | J15: 1.8 | K15: =(TRUNC(F15)=2)*((I$8=0)*IF(F$4=0,0,J15-F$5)+(I$8>0)*(J15-I$8-F$5))+(TRUNC(F15)=1)*((I$8=0)*IF(F$4=0,0,F$4)) -> 0.3 | L15: =IF(F15>2,F$6+0.5*F$7,F$6) -> 9000 | M15: =(C15>0)*L15/I15*IF(OR(F15=1.2,F15=2.2),0.6,1) -> 0 | N15: =(F15=1.1)*F$3+(F15=1.2)*(2*1.25*D15/1000+2*O$8+O$7)/2+(F15=2.1)*(F$3+0.3)+(F15=2.2)*(2*1.25*D15/1000+4*O$8+O$7)/2 -> 1.2 | O15: =((N15*(J15+1.25*D15/1000+0.1)+(TRUNC(F15)=1)*(J15-0.9)^2*O$6)*IF(F15-TRUNC(F15)=0.2,0.5,1))*(C15>0) -> 0 | P15: =O15*C15*IF(O$4=1,1,1/3.28) -> 0 | Q15: =IF(F15-TRUNC(F15)=0.2,0.5,1)*C15*IF(O$4=1,1,1/3.28) -> 0 | R15: =C15*E15*U$3*IF(O$4=1,1,1/3.28) -> 0 | S15: =IF(I$8>0,N15*(0.1+0.00125*D15+I$8)-PI()*(D15*0.00125)^2/4,0)*2*I6*C15*IF(O$4=2,1,1/3.28) -> 0 | T15: =IF(K15=0,0,1)*IF(AND(I$8=0,K15>0),N15*(0.1+0.00125*D15+K15)-PI()*(D15*0.00125)^2/4,N15*K15)*2*I$6*C15*IF(O$4=1,1,1/3.28) -> 0 | U15: =G15+R15+S15+T15 -> 0 | V15: =H15+C15*M15*IF(O$4=1,1,1/3.28) -> 0 | W15: =((IF(S15=0,0,S15/I$4)+IF(T15=0,0,T15/I$6))/2+PI()*(D15*0.00125)^2/4*C15*IF(O$4=1,1,1/3.28))*I$7 -> 0 | X15: =IF(C15=0,0,(U15+V15+W15)/C15) -> 0 | Y15: =U15+V15+W15 -> 0
A16: 4 | E16: =(D16=100)*L$3+(D16=150)*L$4+(D16=200)*L$5+(D16=250)*L$6+(D16=300)*L$7 -> 0 | F16: 1.1 | I16: =IF(F16>2,F$8*0.9,F$8)*(O$3/100) -> 65 | J16: 1.8 | K16: =(TRUNC(F16)=2)*((I$8=0)*IF(F$4=0,0,J16-F$5)+(I$8>0)*(J16-I$8-F$5))+(TRUNC(F16)=1)*((I$8=0)*IF(F$4=0,0,F$4)) -> 0.3 | L16: =IF(F16>2,F$6+0.5*F$7,F$6) -> 9000 | M16: =(C16>0)*L16/I16*IF(OR(F16=1.2,F16=2.2),0.6,1) -> 0 | N16: =(F16=1.1)*F$3+(F16=1.2)*(2*1.25*D16/1000+2*O$8+O$7)/2+(F16=2.1)*(F$3+0.3)+(F16=2.2)*(2*1.25*D16/1000+4*O$8+O$7)/2 -> 1.2 | O16: =((N16*(J16+1.25*D16/1000+0.1)+(TRUNC(F16)=1)*(J16-0.9)^2*O$6)*IF(F16-TRUNC(F16)=0.2,0.5,1))*(C16>0) -> 0 | P16: =O16*C16*IF(O$4=1,1,1/3.28) -> 0 | Q16: =IF(F16-TRUNC(F16)=0.2,0.5,1)*C16*IF(O$4=1,1,1/3.28) -> 0 | R16: =C16*E16*U$3*IF(O$4=1,1,1/3.28) -> 0 | S16: =IF(I$8>0,N16*(0.1+0.00125*D16+I$8)-PI()*(D16*0.00125)^2/4,0)*2*I7*C16*IF(O$4=2,1,1/3.28) -> 0 | T16: =IF(K16=0,0,1)*IF(AND(I$8=0,K16>0),N16*(0.1+0.00125*D16+K16)-PI()*(D16*0.00125)^2/4,N16*K16)*2*I$6*C16*IF(O$4=1,1,1/3.28) -> 0 | U16: =G16+R16+S16+T16 -> 0 | V16: =H16+C16*M16*IF(O$4=1,1,1/3.28) -> 0 | W16: =((IF(S16=0,0,S16/I$4)+IF(T16=0,0,T16/I$6))/2+PI()*(D16*0.00125)^2/4*C16*IF(O$4=1,1,1/3.28))*I$7 -> 0 | X16: =IF(C16=0,0,(U16+V16+W16)/C16) -> 0 | Y16: =U16+V16+W16 -> 0
A17: 5 | E17: =(D17=100)*L$3+(D17=150)*L$4+(D17=200)*L$5+(D17=250)*L$6+(D17=300)*L$7 -> 0 | F17: 1.1 | I17: =IF(F17>2,F$8*0.9,F$8)*(O$3/100) -> 65 | J17: 1.8 | K17: =(TRUNC(F17)=2)*((I$8=0)*IF(F$4=0,0,J17-F$5)+(I$8>0)*(J17-I$8-F$5))+(TRUNC(F17)=1)*((I$8=0)*IF(F$4=0,0,F$4)) -> 0.3 | L17: =IF(F17>2,F$6+0.5*F$7,F$6) -> 9000 | M17: =(C17>0)*L17/I17*IF(OR(F17=1.2,F17=2.2),0.6,1) -> 0 | N17: =(F17=1.1)*F$3+(F17=1.2)*(2*1.25*D17/1000+2*O$8+O$7)/2+(F17=2.1)*(F$3+0.3)+(F17=2.2)*(2*1.25*D17/1000+4*O$8+O$7)/2 -> 1.2 | O17: =((N17*(J17+1.25*D17/1000+0.1)+(TRUNC(F17)=1)*(J17-0.9)^2*O$6)*IF(F17-TRUNC(F17)=0.2,0.5,1))*(C17>0) -> 0 | P17: =O17*C17*IF(O$4=1,1,1/3.28) -> 0 | Q17: =IF(F17-TRUNC(F17)=0.2,0.5,1)*C17*IF(O$4=1,1,1/3.28) -> 0 | R17: =C17*E17*U$3*IF(O$4=1,1,1/3.28) -> 0 | S17: =IF(I$8>0,N17*(0.1+0.00125*D17+I$8)-PI()*(D17*0.00125)^2/4,0)*2*I8*C17*IF(O$4=2,1,1/3.28) -> 0 | T17: =IF(K17=0,0,1)*IF(AND(I$8=0,K17>0),N17*(0.1+0.00125*D17+K17)-PI()*(D17*0.00125)^2/4,N17*K17)*2*I$6*C17*IF(O$4=1,1,1/3.28) -> 0 | U17: =G17+R17+S17+T17 -> 0 | V17: =H17+C17*M17*IF(O$4=1,1,1/3.28) -> 0 | W17: =((IF(S17=0,0,S17/I$4)+IF(T17=0,0,T17/I$6))/2+PI()*(D17*0.00125)^2/4*C17*IF(O$4=1,1,1/3.28))*I$7 -> 0 | X17: =IF(C17=0,0,(U17+V17+W17)/C17) -> 0 | Y17: =U17+V17+W17 -> 0
A18: 6 | E18: =(D18=100)*L$3+(D18=150)*L$4+(D18=200)*L$5+(D18=250)*L$6+(D18=300)*L$7 -> 0 | F18: 1.1 | I18: =IF(F18>2,F$8*0.9,F$8)*(O$3/100) -> 65 | J18: 1.8 | K18: =(TRUNC(F18)=2)*((I$8=0)*IF(F$4=0,0,J18-F$5)+(I$8>0)*(J18-I$8-F$5))+(TRUNC(F18)=1)*((I$8=0)*IF(F$4=0,0,F$4)) -> 0.3 | L18: =IF(F18>2,F$6+0.5*F$7,F$6) -> 9000 | M18: =(C18>0)*L18/I18*IF(OR(F18=1.2,F18=2.2),0.6,1) -> 0 | N18: =(F18=1.1)*F$3+(F18=1.2)*(2*1.25*D18/1000+2*O$8+O$7)/2+(F18=2.1)*(F$3+0.3)+(F18=2.2)*(2*1.25*D18/1000+4*O$8+O$7)/2 -> 1.2 | O18: =((N18*(J18+1.25*D18/1000+0.1)+(TRUNC(F18)=1)*(J18-0.9)^2*O$6)*IF(F18-TRUNC(F18)=0.2,0.5,1))*(C18>0) -> 0 | P18: =O18*C18*IF(O$4=1,1,1/3.28) -> 0 | Q18: =IF(F18-TRUNC(F18)=0.2,0.5,1)*C18*IF(O$4=1,1,1/3.28) -> 0 | R18: =C18*E18*U$3*IF(O$4=1,1,1/3.28) -> 0 | S18: =IF(I$8>0,N18*(0.1+0.00125*D18+I$8)-PI()*(D18*0.00125)^2/4,0)*2*I9*C18*IF(O$4=2,1,1/3.28) -> 0 | T18: =IF(K18=0,0,1)*IF(AND(I$8=0,K18>0),N18*(0.1+0.00125*D18+K18)-PI()*(D18*0.00125)^2/4,N18*K18)*2*I$6*C18*IF(O$4=1,1,1/3.28) -> 0 | U18: =G18+R18+S18+T18 -> 0 | V18: =H18+C18*M18*IF(O$4=1,1,1/3.28) -> 0 | W18: =((IF(S18=0,0,S18/I$4)+IF(T18=0,0,T18/I$6))/2+PI()*(D18*0.00125)^2/4*C18*IF(O$4=1,1,1/3.28))*I$7 -> 0 | X18: =IF(C18=0,0,(U18+V18+W18)/C18) -> 0 | Y18: =U18+V18+W18 -> 0
A20: Pipe Totals = | C20: =SUM(C12:C19) -> 0 | D20: =IF(O4=1,"METERS","FEET") -> METERS | G20: =SUM(G13:G18) -> 0 | H20: =SUM(H13:H18) -> 0 | P20: =SUM(P12:P19) -> 0 | Q20: =SUM(Q12:Q19) -> 0 | R20: =SUM(R12:R19) -> 0 | S20: =SUM(S12:S19) -> 0 | T20: =SUM(T12:T19) -> 0 | U20: =SUM(U12:U19) -> 0 | V20: =SUM(V12:V19) -> 0 | W20: =SUM(W12:W19) -> 0 | Y20: =SUM(Y12:Y19) -> 0
A22: ITM# | B22: SPECIALS | C22: QNTY | D22: $ EACH | E22: TB?y/n | F22: $/ANODE | G22: $LABech | H22: $ LABOR | I22: $ FTNGS | J22: $ CONC | K22: $ EACH | L22: TOTAL $ | N22: ITEM# | O22: VALVES | P22: QNTY | Q22: $/VALVE | R22: $/BOX | S22: $/ANODE | T22: $LAB/V | U22: $ LABOR | V22: $ MATRL | W22: $ EACH | X22: TTL CST
A24: 1 | H24: =G24*C24 -> 0 | I24: =(D24+F24)*C24*U$3 -> 0 | J24: =IF(E24=1,0.5*C24*L$8,0) -> 0 | K24: =IF(C24=0,0,(H24+I24+J24)/C24) -> 0 | L24: =H24+I24+J24 -> 0 | M24: V | N24: 1 | O24: 50 mm | Q24: 424 | R24: 285 | S24: 150 | U24: =P24*T24 -> 0 | V24: =P24*(Q24+R24+S24)*U$3 -> 0 | W24: =IF(P24=0,0,(U24+V24)/P24) -> 0 | X24: =U24+V24 -> 0
A25: =1+A24 -> 2 | H25: =G25*C25 -> 0 | I25: =(D25+F25)*C25*U$3 -> 0 | J25: =IF(E25=1,0.5*C25*L$8,0) -> 0 | K25: =IF(C25=0,0,(H25+I25+J25)/C25) -> 0 | L25: =H25+I25+J25 -> 0 | M25: A | N25: 2 | O25: 100mm | Q25: 807 | R25: 285 | S25: 150 | U25: =P25*T25 -> 0 | V25: =P25*(Q25+R25+S25)*U$3 -> 0 | W25: =IF(P25=0,0,(U25+V25)/P25) -> 0 | X25: =U25+V25 -> 0
A26: =1+A25 -> 3 | H26: =G26*C26 -> 0 | I26: =(D26+F26)*C26*U$3 -> 0 | J26: =IF(E26=1,0.5*C26*L$8,0) -> 0 | K26: =IF(C26=0,0,(H26+I26+J26)/C26) -> 0 | L26: =H26+I26+J26 -> 0 | M26: L | N26: 3 | O26: 150mm | Q26: 1027 | R26: 285 | S26: 150 | U26: =P26*T26 -> 0 | V26: =P26*(Q26+R26+S26)*U$3 -> 0 | W26: =IF(P26=0,0,(U26+V26)/P26) -> 0 | X26: =U26+V26 -> 0
A27: =1+A26 -> 4 | H27: =G27*C27 -> 0 | I27: =(D27+F27)*C27*U$3 -> 0 | J27: =IF(E27=1,0.5*C27*L$8,0) -> 0 | K27: =IF(C27=0,0,(H27+I27+J27)/C27) -> 0 | L27: =H27+I27+J27 -> 0 | M27: V | N27: 4 | O27: 200mm | Q27: 1732 | R27: 285 | S27: 150 | U27: =P27*T27 -> 0 | V27: =P27*(Q27+R27+S27)*U$3 -> 0 | W27: =IF(P27=0,0,(U27+V27)/P27) -> 0 | X27: =U27+V27 -> 0
A28: =1+A27 -> 5 | H28: =G28*C28 -> 0 | I28: =(D28+F28)*C28*U$3 -> 0 | J28: =IF(E28=1,0.5*C28*L$8,0) -> 0 | K28: =IF(C28=0,0,(H28+I28+J28)/C28) -> 0 | L28: =H28+I28+J28 -> 0 | M28: E | N28: 5 | O28: 250mm | Q28: 2665 | R28: 285 | S28: 150 | U28: =P28*T28 -> 0 | V28: =P28*(Q28+R28+S28)*U$3 -> 0 | W28: =IF(P28=0,0,(U28+V28)/P28) -> 0 | X28: =U28+V28 -> 0
A29: =1+A28 -> 6 | H29: =G29*C29 -> 0 | I29: =(D29+F29)*C29*U$3 -> 0 | J29: =IF(E29=1,0.5*C29*L$8,0) -> 0 | K29: =IF(C29=0,0,(H29+I29+J29)/C29) -> 0 | L29: =H29+I29+J29 -> 0 | M29: S | N29: 6 | O29: 300mm | Q29: 3696 | R29: 285 | S29: 150 | U29: =P29*T29 -> 0 | V29: =P29*(Q29+R29+S29)*U$3 -> 0 | W29: =IF(P29=0,0,(U29+V29)/P29) -> 0 | X29: =U29+V29 -> 0
A30: =1+A29 -> 7 | H30: =G30*C30 -> 0 | I30: =(D30+F30)*C30*U$3 -> 0 | J30: =IF(E30=1,0.5*C30*L$8,0) -> 0 | K30: =IF(C30=0,0,(H30+I30+J30)/C30) -> 0 | L30: =H30+I30+J30 -> 0 | N30: Totals | P30: =SUM(P23:P29) -> 0 | U30: =SUM(U22:U29) -> 0 | V30: =SUM(V22:V29) -> 0 | X30: =SUM(X24:X29) -> 0
A31: =1+A30 -> 8 | H31: =G31*C31 -> 0 | I31: =(D31+F31)*C31*U$3 -> 0 | J31: =IF(E31=1,0.5*C31*L$8,0) -> 0 | K31: =IF(C31=0,0,(H31+I31+J31)/C31) -> 0 | L31: =H31+I31+J31 -> 0
A32: =1+A31 -> 9 | H32: =G32*C32 -> 0 | I32: =(D32+F32)*C32*U$3 -> 0 | J32: =IF(E32=1,0.5*C32*L$8,0) -> 0 | K32: =IF(C32=0,0,(H32+I32+J32)/C32) -> 0 | L32: =H32+I32+J32 -> 0 | N32: HYDRANTS | O32: QNTY | P32: $/HYDR. | Q32: $/VALVE | R32: $/BOX | S32: $/LAB ea | T32: $CONC TB | U32: $/X MATRL | V32: $ LABOR | W32: $ MATRL | X32: $/SET | Y32: TTL CST
A33: =1+A32 -> 10 | H33: =G33*C33 -> 0 | I33: =(D33+F33)*C33*U$3 -> 0 | J33: =IF(E33=1,0.5*C33*L$8,0) -> 0 | K33: =IF(C33=0,0,(H33+I33+J33)/C33) -> 0 | L33: =H33+I33+J33 -> 0 | N33: TOTALS | P33: 4500 | Q33: 1027 | R33: 285 | S33: 500 | T33: 150 | U33: 240 | V33: =S33*O33 -> 0 | W33: =O33*(P33+Q33+R33+T33+U33) -> 0 | X33: =W33+V33 -> 0 | Y33: =V33+W33 -> 0
A34: =1+A33 -> 11 | H34: =G34*C34 -> 0 | I34: =(D34+F34)*C34*U$3 -> 0 | J34: =IF(E34=1,0.5*C34*L$8,0) -> 0 | K34: =IF(C34=0,0,(H34+I34+J34)/C34) -> 0 | L34: =H34+I34+J34 -> 0
A35: =1+A34 -> 12 | H35: =G35*C35 -> 0 | I35: =(D35+F35)*C35*U$3 -> 0 | J35: =IF(E35=1,0.5*C35*L$8,0) -> 0 | K35: =IF(C35=0,0,(H35+I35+J35)/C35) -> 0 | L35: =H35+I35+J35 -> 0 | M35: R | N35: RISERS | O35: QNTY | P35: $/BEND | Q35: $/FL-PE | R35: $/X MTRL | S35: $/RODDING | T35: $/L&E | U35: $CONC TB | V35: $L&E | W35: $MATRL | X35: $/SET | Y35: TTL CST
A36: =1+A35 -> 13 | H36: =G36*C36 -> 0 | I36: =(D36+F36)*C36*U$3 -> 0 | J36: =IF(E36=1,0.5*C36*L$8,0) -> 0 | K36: =IF(C36=0,0,(H36+I36+J36)/C36) -> 0 | L36: =H36+I36+J36 -> 0 | M36: I | N36: 100mm | P36: 91 | Q36: 450 | R36: 355 | S36: 150 | T36: 1500 | U36: =O36*(250*U3) -> 0 | V36: =O36*T36 -> 0 | W36: =O36*(P36+Q36+R36+S36)*U3+O36*U36 -> 0 | X36: =IF(O36=0,0,(V36+W36)/O36) -> 0 | Y36: =V36+W36 -> 0
A37: =1+A36 -> 14 | H37: =G37*C37 -> 0 | I37: =(D37+F37)*C37*U$3 -> 0 | J37: =IF(E37=1,0.5*C37*L$8,0) -> 0 | K37: =IF(C37=0,0,(H37+I37+J37)/C37) -> 0 | L37: =H37+I37+J37 -> 0 | M37: S | N37: 150mm | P37: 147 | Q37: 560 | R37: 430 | S37: 150 | T37: 1500 | U37: =O37*(250*U3) -> 0 | V37: =O37*T37 -> 0 | W37: =O37*(P37+Q37+R37+S37)*U3+O37*U37 -> 0 | X37: =IF(O37=0,0,(V37+W37)/O37) -> 0 | Y37: =V37+W37 -> 0
A38: =1+A37 -> 15 | H38: =G38*C38 -> 0 | I38: =(D38+F38)*C38*U$3 -> 0 | J38: =IF(E38=1,0.5*C38*L$8,0) -> 0 | K38: =IF(C38=0,0,(H38+I38+J38)/C38) -> 0 | L38: =H38+I38+J38 -> 0 | M38: E | N38: 200mm | P38: 200 | Q38: 720 | R38: 690 | S38: 150 | T38: 1500 | U38: 0 | V38: =O38*T38 -> 0 | W38: =O38*(P38+Q38+R38+S38)*U3+O38*U38 -> 0 | X38: =IF(O38=0,0,(V38+W38)/O38) -> 0 | Y38: =V38+W38 -> 0
A39: =1+A38 -> 16 | H39: =G39*C39 -> 0 | I39: =(D39+F39)*C39*U$3 -> 0 | J39: =IF(E39=1,0.5*C39*L$8,0) -> 0 | K39: =IF(C39=0,0,(H39+I39+J39)/C39) -> 0 | L39: =H39+I39+J39 -> 0 | M39: R | N39: 250mm | P39: 336 | Q39: 810 | R39: 828 | S39: 150 | T39: 1500 | U39: =O39*(250*U3) -> 0 | V39: =O39*T39 -> 0 | W39: =O39*(P39+Q39+R39+S39)*U3+O39*U39 -> 0 | X39: =IF(O39=0,0,(V39+W39)/O39) -> 0 | Y39: =V39+W39 -> 0
A40: =1+A39 -> 17 | H40: =G40*C40 -> 0 | I40: =(D40+F40)*C40*U$3 -> 0 | J40: =IF(E40=1,0.5*C40*L$8,0) -> 0 | K40: =IF(C40=0,0,(H40+I40+J40)/C40) -> 0 | L40: =H40+I40+J40 -> 0 | M40: S | N40: 300mm | P40: 452 | Q40: 1020 | R40: 955 | S40: 150 | T40: 1500 | U40: =O40*(250*U3) -> 0 | V40: =O40*T40 -> 0 | W40: =O40*(P40+Q40+R40+S40)*U3+O40*U40 -> 0 | X40: =IF(O40=0,0,(V40+W40)/O40) -> 0 | Y40: =V40+W40 -> 0
A41: =1+A40 -> 18 | H41: =G41*C41 -> 0 | I41: =(D41+F41)*C41*U$3 -> 0 | J41: =IF(E41=1,0.5*C41*L$8,0) -> 0 | K41: =IF(C41=0,0,(H41+I41+J41)/C41) -> 0 | L41: =H41+I41+J41 -> 0 | N41: TTL RISER | O41: =SUM(O34:O40) -> 0 | U41: =SUM(U34:U40) -> 0 | V41: =SUM(V34:V40) -> 0 | W41: =SUM(W34:W40) -> 0 | Y41: =SUM(Y34:Y40) -> 0
A42: =1+A41 -> 19 | H42: =G42*C42 -> 0 | I42: =(D42+F42)*C42*U$3 -> 0 | J42: =IF(E42=1,0.5*C42*L$8,0) -> 0 | K42: =IF(C42=0,0,(H42+I42+J42)/C42) -> 0 | L42: =H42+I42+J42 -> 0
A43: =1+A42 -> 20 | H43: =G43*C43 -> 0 | I43: =(D43+F43)*C43*U$3 -> 0 | J43: =IF(E43=1,0.5*C43*L$8,0) -> 0 | K43: =IF(C43=0,0,(H43+I43+J43)/C43) -> 0 | L43: =H43+I43+J43 -> 0
A44: =1+A43 -> 21 | H44: =G44*C44 -> 0 | I44: =(D44+F44)*C44*U$3 -> 0 | J44: =IF(E44=1,0.5*C44*L$8,0) -> 0 | K44: =IF(C44=0,0,(H44+I44+J44)/C44) -> 0 | L44: =H44+I44+J44 -> 0
A45: =1+A44 -> 22 | H45: =G45*C45 -> 0 | I45: =(D45+F45)*C45*U$3 -> 0 | J45: =IF(E45=1,0.5*C45*L$8,0) -> 0 | K45: =IF(C45=0,0,(H45+I45+J45)/C45) -> 0 | L45: =H45+I45+J45 -> 0
A46: =1+A45 -> 23 | H46: =G46*C46 -> 0 | I46: =(D46+F46)*C46*U$3 -> 0 | J46: =IF(E46=1,0.5*C46*L$8,0) -> 0 | K46: =IF(C46=0,0,(H46+I46+J46)/C46) -> 0 | L46: =H46+I46+J46 -> 0
A47: =1+A46 -> 24 | H47: =G47*C47 -> 0 | I47: =(D47+F47)*C47*U$3 -> 0 | J47: =IF(E47=1,0.5*C47*L$8,0) -> 0 | K47: =IF(C47=0,0,(H47+I47+J47)/C47) -> 0 | L47: =H47+I47+J47 -> 0
A48: =1+A47 -> 25 | H48: =G48*C48 -> 0 | I48: =(D48+F48)*C48*U$3 -> 0 | J48: =IF(E48=1,0.5*C48*L$8,0) -> 0 | K48: =IF(C48=0,0,(H48+I48+J48)/C48) -> 0 | L48: =H48+I48+J48 -> 0
A49: =1+A48 -> 26 | H49: =G49*C49 -> 0 | I49: =(D49+F49)*C49*U$3 -> 0 | J49: =IF(E49=1,0.5*C49*L$8,0) -> 0 | K49: =IF(C49=0,0,(H49+I49+J49)/C49) -> 0 | L49: =H49+I49+J49 -> 0
A50: =1+A49 -> 27 | H50: =G50*C50 -> 0 | I50: =(D50+F50)*C50*U$3 -> 0 | J50: =IF(E50=1,0.5*C50*L$8,0) -> 0 | K50: =IF(C50=0,0,(H50+I50+J50)/C50) -> 0 | L50: =H50+I50+J50 -> 0
A51: =1+A50 -> 28 | H51: =G51*C51 -> 0 | I51: =(D51+F51)*C51*U$3 -> 0 | J51: =IF(E51=1,0.5*C51*L$8,0) -> 0 | K51: =IF(C51=0,0,(H51+I51+J51)/C51) -> 0 | L51: =H51+I51+J51 -> 0
A52: =1+A51 -> 29 | H52: =G52*C52 -> 0 | I52: =(D52+F52)*C52*U$3 -> 0 | J52: =IF(E52=1,0.5*C52*L$8,0) -> 0 | K52: =IF(C52=0,0,(H52+I52+J52)/C52) -> 0 | L52: =H52+I52+J52 -> 0
A53: =1+A52 -> 30 | H53: =G53*C53 -> 0 | I53: =(D53+F53)*C53*U$3 -> 0 | J53: =IF(E53=1,0.5*C53*L$8,0) -> 0 | K53: =IF(C53=0,0,(H53+I53+J53)/C53) -> 0 | L53: =H53+I53+J53 -> 0
A54: =1+A53 -> 31 | B54: 300 One Locks | D54: 267 | F54: 100 | H54: =G54*C54 -> 0 | I54: =(D54+F54)*C54*U$3 -> 0 | J54: =IF(E54=1,0.5*C54*L$8,0) -> 0 | K54: =IF(C54=0,0,(H54+I54+J54)/C54) -> 0 | L54: =H54+I54+J54 -> 0
A55: =1+A54 -> 32 | B55: 250 One Locks | D55: 188 | F55: 100 | H55: =G55*C55 -> 0 | I55: =(D55+F55)*C55*U$3 -> 0 | J55: =IF(E55=1,0.5*C55*L$8,0) -> 0 | K55: =IF(C55=0,0,(H55+I55+J55)/C55) -> 0 | L55: =H55+I55+J55 -> 0
A56: =1+A55 -> 33 | B56: 200 One Locks | D56: 112 | F56: 100 | H56: =G56*C56 -> 0 | I56: =(D56+F56)*C56*U$3 -> 0 | J56: =IF(E56=1,0.5*C56*L$8,0) -> 0 | K56: =IF(C56=0,0,(H56+I56+J56)/C56) -> 0 | L56: =H56+I56+J56 -> 0
A57: =1+A56 -> 34 | B57: 150 One Locks | D57: 85 | F57: 100 | H57: =G57*C57 -> 0 | I57: =(D57+F57)*C57*U$3 -> 0 | J57: =IF(E57=1,0.5*C57*L$8,0) -> 0 | K57: =IF(C57=0,0,(H57+I57+J57)/C57) -> 0 | L57: =H57+I57+J57 -> 0
A58: =1+A57 -> 35 | B58: 100 One Locks | D58: 69 | F58: 100 | H58: =G58*C58 -> 0 | I58: =(D58+F58)*C58*U$3 -> 0 | J58: =IF(E58=1,0.5*C58*L$8,0) -> 0 | K58: =IF(C58=0,0,(H58+I58+J58)/C58) -> 0 | L58: =H58+I58+J58 -> 0
A59: =1+A58 -> 36 | H59: =G59*C59 -> 0 | I59: =(D59+F59)*C59*U$3 -> 0 | J59: =IF(E59=1,0.5*C59*L$8,0) -> 0 | K59: =IF(C59=0,0,(H59+I59+J59)/C59) -> 0 | L59: =H59+I59+J59 -> 0
A60: =1+A59 -> 37 | B60: TESTING | C60: 1 | G60: 6500 | H60: =G60*C60 -> 6500 | I60: =(D60+F60)*C60*U$3 -> 0 | J60: =IF(E60=1,0.5*C60*L$8,0) -> 0 | K60: =IF(C60=0,0,(H60+I60+J60)/C60) -> 6500 | L60: =H60+I60+J60 -> 6500
A62: Specials Totals = | C62: =SUM(C24:C60) -> 1 | H62: =SUM(H23:H61) -> 6500 | I62: =SUM(I24:I61) -> 0 | J62: =SUM(J23:J61) -> 0 | L62: =SUM(L23:L61) -> 6500
B64: MISCELLANEOUS | C64: QNTY | D64: TAXFCT | E64: $/MATRL | F64: $/L&E | G64: $MATRL | H64: $L&E | I64: $ EACH | J64: TOTAL$
A65: 1 | B65: TRACER | C65: =C20 -> 0 | D65: =U$3 -> 1 | E65: =IF(O$4=1,1.25,1.25/3.28) -> 1.25 | G65: =C65*D65*IF(O$4=1,E65,E65/3.28) -> 0 | H65: =C65*F65 -> 0 | I65: =IF(C65=0,0,(G65+H65)/C65) -> 0 | J65: =G65+H65 -> 0
A66: 2 | C66: 0 | D66: =U$3 -> 1 | E66: 0 | G66: =C66*D66*E66 -> 0 | H66: =C66*F66 -> 0 | I66: =IF(C66=0,0,(G66+H66)/C66) -> 0 | J66: =G66+H66 -> 0
A67: 3 | D67: =U$3 -> 1 | E67: 0 | G67: =C67*D67*E67 -> 0 | H67: =C67*F67 -> 0 | I67: =IF(C67=0,0,(G67+H67)/C67) -> 0 | J67: =G67+H67 -> 0
A68: 4 | D68: =U$3 -> 1 | E68: 0 | G68: =C68*D68*E68 -> 0 | H68: =C68*F68 -> 0 | I68: =IF(C68=0,0,(G68+H68)/C68) -> 0 | J68: =G68+H68 -> 0
A69: 5 | D69: =U$3 -> 1 | E69: 0 | G69: =C69*D69*E69 -> 0 | H69: =C69*F69 -> 0 | I69: =IF(C69=0,0,(G69+H69)/C69) -> 0 | J69: =G69+H69 -> 0
A70: 6 | D70: =U$3 -> 1 | E70: 0 | G70: =C70*D70*E70 -> 0 | H70: =C70*F70 -> 0 | I70: =IF(C70=0,0,(G70+H70)/C70) -> 0 | J70: =G70+H70 -> 0
A71: 7 | D71: =U$3 -> 1 | E71: 0 | G71: =C71*D71*E71 -> 0 | H71: =C71*F71 -> 0 | I71: =IF(C71=0,0,(G71+H71)/C71) -> 0 | J71: =G71+H71 -> 0
A72: 8 | D72: =U$3 -> 1 | E72: 0 | G72: =C72*D72*E72 -> 0 | H72: =C72*F72 -> 0 | I72: =IF(C72=0,0,(G72+H72)/C72) -> 0 | J72: =G72+H72 -> 0
A74: Totals Miscellaneous = | G74: =SUM(G65:G73) -> 0 | H74: =SUM(H65:H73) -> 0 | I74: =SUM(I65:I73) -> 0 | J74: =SUM(J65:J73) -> 0 | U74: ITEM | V74: $ COST | W74: MARGIN | Y74: SALE $
B76: $ Pipe | C76: =R20 -> 0 | F76: $Concrete | G76: =T33+J62+U41 -> 150 | I76: CMExca | J76: =P20 -> 0 | U76: MATERIAL | V76: =U20+V30+W33+I62+J62+W41+G74 -> 0 | W76: =(O$5-1)*V76 -> 0 | Y76: =V76+W76 -> 0
B77: $ Valves & Boxes | C77: =V30+O33*(Q33+R33) -> 0 | F77: $Crush Stone | G77: =S20 -> 0 | I77: Days | J77: =(V20+U30+V33+H62+V41+H74)/F6 -> 0.72222222 | L77: $/CM Exc= | M77: =IF(J76=0,0,(V20+U30+V33+H62+V41+H74)/J76) -> 0 | U77: LAB&EQ. | V77: =V20+U30+V33+H62+V41+H74 -> 6500 | W77: =(O$5-1)*V77 -> 650 | Y77: =V77+W77 -> 7150
B78: $ Hydrants | C78: =O33*P33 -> 0 | F78: $Granular | G78: =T20 -> 0 | I78: M Pipe | J78: =IF(O4=1,C20,C20/3.28) -> 0 | L78: $/M Pipe= | M78: =IF(J78=0,0,(V20+U30+V33+H62+V41+H74)/J78) -> 0 | U78: TRUCKING | V78: =W20 -> 0 | W78: =(O$5-1)*V78 -> 0 | Y78: =V78+W78 -> 0
B79: $Fittings | C79: =I62+O36*(P36+Q36+S36)+O37*(P37+Q37+S37)+O38*(P38+Q38+S38)+O39*(P39+Q39+S39) -> 0 | F79: CM Conc | G79: =IF(G76=0,0,G76/L8) -> 0.6 | I79: Ft Pipe | J79: =J78*3.28 -> 0 | L79: $/FtPipe= | M79: =M78/3.28 -> 0
B80: $ WATERMAIN MATRL | C80: =SUM(C76:C79) -> 0 | F80: ImpTons Stone | G80: =IF(G77=0,0,G77/I3) -> 0 | I80: M Trnch | J80: =Q20 -> 0 | L80: $/M Trnch= | M80: =IF(J80=0,0,(V20+U30+V33+H62+V41+H74)/J80) -> 0 | P80: % Lab&Eqp | Q80: %Matrl | R80: %Trkng
B81: $ Miscellaneous | C81: =G74 -> 0 | F81: ImpTonsGran | G81: =IF(G78=0,0,G78/I5) -> 0 | I81: FtTrnch | J81: =J80*3.28 -> 0 | L81: $/FtTrnch= | M81: =M80/3.28 -> 0 | P81: =IF(V77=0,0,V77/(V76+V77+V78)*100) -> 100 | Q81: =IF(V76=0,0,V76/(V76+V77+V78)*100) -> 0 | R81: =IF(P81=0,0,100-P81-Q81) -> 0 | U81: BID | V81: =SUM(V75:V79) -> 6500 | W81: =SUM(W75:W79) -> 650 | Y81: =SUM(Y75:Y79) -> 7150
B82: $ Xtra Materials | C82: =G20+O33*U33+O36*R36+O37*R37+O38*R38+O39*R39 -> 0

Sheet SUMMARY OF ESTIMATE
C1: SUMMARY OF ESTIMATE
L2: =B3 -> 0
A3: ='MANHOLES (1)'!A2 -> PROJECT | B3: ='MANHOLES (1)'!B2 -> 0
B4: ='MANHOLES (1)'!B3 -> 0
A6: ='MANHOLES (1)'!A5 -> Date: | B6: ='MANHOLES (1)'!B5 -> 0
C10: ITEM | D10: MATERIALS | F10: Labour & Equipment | I10: TRUCKING | L10: SUB TOTAL | M10: TOTALS
A11: ='SEWERS (1)'!C57 -> 0 | B11: m | C11: SEWER (1) | D11: ='SEWERS (1)'!Z62 -> 10000 | F11: ='SEWERS (1)'!Z63 -> 0 | I11: ='SEWERS (1)'!Z64 -> 0 | L11: ='SEWERS (1)'!Z67 -> 10000 | M11: ='SEWERS (1)'!AB67 -> 11000
C12: MANHOLES (1) | D12: ='MANHOLES (1)'!T54 -> 0 | F12: ='MANHOLES (1)'!T55 -> 0 | I12: ='MANHOLES (1)'!T56 -> 0 | L12: ='MANHOLES (1)'!T57 -> 0 | M12: ='MANHOLES (1)'!V57 -> 0
A13: ='WATERMAIN (1)'!Q20 -> 0 | B13: m | C13: WATERMAIN (1) | D13: ='WATERMAIN (1)'!V76 -> 0 | F13: ='WATERMAIN (1)'!V77 -> 6500 | I13: ='WATERMAIN (1)'!V78 -> 0 | L13: ='WATERMAIN (1)'!V81 -> 6500 | M13: ='WATERMAIN (1)'!Y81 -> 7150
C14: TOTALS | D14: =SUM(D11:D13) -> 10000 | F14: =SUM(F11:F13) -> 6500 | I14: =SUM(I11:I13) -> 0 | L14: =SUM(L11:L13) -> 16500 | M14: =SUM(M11:M13) -> 18150
C15: % | D15: =ROUND(D14/L14*100,1) -> 60.6 | E15: % | F15: =ROUND(F14/L14*100,1) -> 39.4 | G15: % | I15: =ROUND(I14/L14*100,1) -> 0 | J15: %
C18: QUANTITY OF PIPE : | D18: =SUM(A11:A13) -> 0 | E18: meters | I18: TOTAL | L18: =L14 -> 16500
I19: M.U. % | J19: 0.15 | L19: =M14-L18 -> 1650
C20: PRODUCTION DAYS : | D20: =ROUND(F14/'SEWERS (1)'!F6,2) -> 0.72 | E20: day's | L20: =L18+L19 -> 18150
G21: ONSITE | H21: 3 | I21: =I14/'MANHOLES (1)'!F3 -> 0 | J21: m3
C22: DAILY AVG. PROD : | D22: =ROUND(D18/D20,2) -> 0 | E22: m / day | G22: OFFSITE ADDER | H22: 40
